Workbook
Name _Hlk157872730: 文字計畫資訊!$B$389
Name _Hlk161528044: 文字計畫資訊!$A$235
Name _Toc383670581: 文字計畫資訊!$B$74

Sheet 計畫經費彙總表
A1: 五常物業規劃顧問股份(閉鎖型)有限公司
A2: 經費累計表(應按月編制)
A3: 中華民國113年07月01日至114年06月30日
M4: 金額單位：元
B5: 計畫預算數 | E5: 上期累計支用數(列印時請隱藏此欄位) | H5: 本期支用數 | K5: 累計支用數
A6: 預算科目 | B6: 補助款 | C6: 自籌款 | D6: 小計 | E6: 補助款 | F6: 自籌款 | G6: 小計 | H6: 補助款 | I6: 自籌款 | J6: 小計 | K6: 補助款 | L6: 自籌款 | M6: 小計
A7: 一、人事費
A8: 1.計畫人員 | B8: =計畫架構圖表!F105*1000*0.45 -> 463712.4 | C8: =計畫架構圖表!F105*1000*0.55 -> 566759.6 | D8: =B8+C8 -> 1030472 | G8: =E8+F8 -> 0 | H8: =IF(J8+G8>=D8,B8-E8,ROUND(J8/D8*B8,0)) -> 48450 | I8: =J8-H8 -> 59216 | J8: =ROUND(人事費!I13,0) -> 107666 | K8: =E8+H8 -> 48450 | L8: =F8+I8 -> 59216 | M8: =K8+L8 -> 107666
A9: 2.顧問 | B9: =計畫架構圖表!F103*0.45*1000 -> 90000 | C9: =計畫架構圖表!F103*0.55*1000 -> 110000 | D9: =B9+C9 -> 200000 | G9: =E9+F9 -> 0 | H9: =IF(J9+G9>=D9,B9-E9,ROUND(J9/D9*B9,0)) -> 9000 | I9: =J9-H9 -> 11000 | J9: =ROUND(顧問!E15,0) -> 20000 | K9: =E9+H9 -> 9000 | L9: =F9+I9 -> 11000 | M9: =K9+L9 -> 20000
A10: 二、消耗性器材及原材料費 | B10: =計畫架構圖表!F98*1000*0.45 -> 117000 | C10: =計畫架構圖表!F98*1000*0.55 -> 143000 | D10: =B10+C10 -> 260000 | G10: =E10+F10 -> 0 | H10: =IF(J10+G10>=D10,B10-E10,ROUND(J10/D10*B10,0)) -> 1706 | I10: =J10-H10 -> 2084 | J10: =ROUND(材料費!J27,0) -> 3790 | K10: =E10+H10 -> 1706 | L10: =F10+I10 -> 2084 | M10: =K10+L10 -> 3790
A11: 三、研發設備使用費 | B11: =計畫架構圖表!F99*1000/60*12/0.45 -> 65502.222 | C11: =計畫架構圖表!F99*1000/60*12*0.55 -> 16211.8 | D11: =B11+C11 -> 81714.022 | G11: =E11+F11 -> 0 | H11: =IF(J11+G11>=D11,B11-E11,ROUND(J11/D11*B11,0)) -> 4770 | I11: =J11-H11 -> 3180 | J11: =ROUND(設備使用費!K29,0) -> 7950 | K11: =E11+H11 -> 4770 | L11: =F11+I11 -> 3180 | M11: =K11+L11 -> 7950
A12: 四、研發設備維護費 | B12: =計畫架構圖表!F99*1000*0.05*0.45 -> 3316.05 | C12: =計畫架構圖表!F99*1000*0.05*0.55 -> 4052.95 | D12: =B12+C12 -> 7369 | G12: =E12+F12 -> 0 | H12: =IF(J12+G12>=D12,B12-E12,ROUND(J12/D12*B12,0)) -> 0 | I12: =J12-H12 -> 0 | J12: =ROUND(設備維護費!M16,0) -> 0 | K12: =E12+H12 -> 0 | L12: =F12+I12 -> 0 | M12: =K12+L12 -> 0
A13: 五、技術移轉費
A14: 1.技術或智慧財產權購買費 | B14: =計畫架構圖表!F101*1000*0.45 -> 450000 | C14: =計畫架構圖表!F101*1000*0.55 -> 550000 | D14: =B14+C14 -> 1000000 | G14: =E14+F14 -> 0 | H14: =IF(J14+G14>=D14,B14-E14,ROUND(J14/D14*B14,0)) -> 135000 | I14: =J14-H14 -> 165000 | J14: =ROUND(技術購買費!F15,0) -> 300000 | K14: =E14+H14 -> 135000 | L14: =F14+I14 -> 165000 | M14: =K14+L14 -> 300000
A15: 2.委託研究費 | B15: =計畫架構圖表!F100*1000*0.45 -> 225000 | C15: =計畫架構圖表!F100*1000*0.55 -> 275000 | D15: =B15+C15 -> 500000 | G15: =E15+F15 -> 0 | H15: =IF(J15+G15>=D15,B15-E15,ROUND(J15/D15*B15,0)) -> 157500 | I15: =J15-H15 -> 192500 | J15: =ROUND(委託研究費!F15,0) -> 350000 | K15: =E15+H15 -> 157500 | L15: =F15+I15 -> 192500 | M15: =K15+L15 -> 350000
A16: 3.委託勞務費 | B16: =計畫架構圖表!F98*1000*45% -> 117000 | C16: =計畫架構圖表!F98*1000*55% -> 143000 | D16: =B16+C16 -> 260000 | G16: =E16+F16 -> 0 | H16: =IF(J16+G16>=D16,B16-E16,ROUND(J16/D16*B16,0)) -> 117000 | I16: =J16-H16 -> 283000 | J16: =ROUND(委託勞務費!F15,0) -> 400000 | K16: =E16+H16 -> 117000 | L16: =F16+I16 -> 283000 | M16: =K16+L16 -> 400000
A17: 六、差旅費
A18: 1.國內差旅費 | B18: 5000 | C18: 10000 | D18: =B18+C18 -> 15000 | G18: =E18+F18 -> 0 | H18: =IF(J18+G18>=D18,B18-E18,ROUND(J18/D18*B18,0)) -> 617 | I18: =J18-H18 -> 1233 | J18: =ROUND(國內差旅費!N14,0) -> 1850 | K18: =E18+H18 -> 617 | L18: =F18+I18 -> 1233 | M18: =K18+L18 -> 1850
A19: 2.國外差旅費 | C19: 0 | D19: =B19+C19 -> 0 | G19: =E19+F19 -> 0 | H19: 0 | I19: =J19-H19 -> 2000 | J19: =ROUND(國外差旅費!N14,0) -> 2000 | K19: =E19+H19 -> 0 | L19: =F19+I19 -> 2000 | M19: =K19+L19 -> 2000
A20: 七、市場驗證費 | B20: =計畫架構圖表!F102*1000*0.45 -> 253890 | C20: =計畫架構圖表!F102*1000*0.55 -> 310310 | D20: =B20+C20 -> 564200 | G20: =E20+F20 -> 0 | H20: =IF(J20+G20>=D20,B20-E20,ROUND(J20/D20*B20,0)) -> 3240 | I20: =J20-H20 -> 3960 | J20: =ROUND(市場驗證費!J18,0) -> 7200 | K20: =E20+H20 -> 3240 | L20: =F20+I20 -> 3960 | M20: =K20+L20 -> 7200
A21: 合 計 | B21: =SUM(B8:B20) -> 1790420.7 | C21: =SUM(C8:C20) -> 2128334.4 | D21: =SUM(D8:D20) -> 3918755 | E21: =SUM(E8:E20) -> 0 | F21: =SUM(F8:F20) -> 0 | G21: =SUM(G8:G20) -> 0 | H21: =SUM(H8:H20) -> #VALUE! | I21: =SUM(I8:I20) -> #VALUE! | ... M21: =SUM(M8:M20) -> #VALUE!
A23: 註1:金額以元為單位。
A24: 註2:補助款及自籌款出現#DIV/0!之欄位請填0。
A25: 註3:請填寫綠色填滿之欄位，電腦會自動編列小計。
A26: 註4:列印時請隱藏「上期累計實支數」之欄位
A28: 公司負責人: | C28: 計畫主持人: | H28: 主辦會計: | K28: 填表人：

Sheet 計畫架構圖表
B1: 創新AI系統整合營運中心服務機制開發運用計畫
P2: 單位/千元
B3: 計畫項目 | C3: =人事費!A7 -> 1.阮氏泉 | E3: 7月 | F3: 8月 | G3: 9月 | H3: 10月 | I3: 11月 | J3: 12月 | K3: 1月 | L3: 2月 | M3: 3月 | N3: 4月 | O3: 5月 | P3: 6月
C4: A分項計畫 商業資訊中心設置計畫 | Q4: 合計 | R4: 細項小計及權重
C5: A1直營商店營運權力取得及技術轉移7/10 | D5: 人 | E5: 0.25 | J5: 0.25 | Q5: =SUM(E5:P5)*49.849 -> 24.9245 | R5: =Q5+Q6 -> 1024.9245
D6: 費 | E6: 500 | J6: 500 | Q6: =SUM(E6:E6:P6) -> 1000 | R6: =R5/F106 -> 0.27243762
C7: A2直營咖啡店營運、進行員工教學及產品開發研究、並導入點餐系統8/1 | D7: 人 | F7: 0.4 | G7: 0.4 | H7: 0.4 | I7: 0.4 | J7: 0.4 | K7: 0.4 | L7: 0.4 | M7: 0.4 | N7: 0.4 | O7: 0.4 | P7: 0.5 | Q7: =SUM(E7:P7)*49.849 -> 224.3205 | R7: =Q7+Q8 -> 484.3205
D8: 費 | F8: 26 | G8: 26 | H8: 26 | I8: 26 | J8: 26 | K8: 26 | L8: 26 | M8: 26 | N8: 26 | O8: 26 | Q8: =SUM(E8:P8) -> 260 | R8: =R7/F106 -> 0.12873839
C9: A3轄內商業資訊收集建檔及資料分析11/1 | D9: 人 | F9: 0.25 | G9: 0.25 | H9: 0.25 | I9: 0.25 | Q9: =SUM(E9:P9)*49.849 -> 49.849 | R9: =Q9+Q10 -> 49.849
D10: 費 | Q10: =SUM(E10:P10) -> 0 | R10: =R9/F106 -> 0.013250481
C11: A4開發商業會員參與聯合營運計畫10/1 | D11: 人 | E11: 0.25 | F11: 0.25 | G11: 0.25 | H11: 0.25 | Q11: =SUM(E11:P11)*49.849 -> 49.849 | R11: =Q11+Q10 -> 49.849
D12: 費 | Q12: =SUM(E12:P12) -> 0 | R12: =R11/F106 -> 0.013250481
C13: A5完成全區域內商業分析報告及擬定顧問企劃，提高直營商業營業額至每月20萬元。4/1 | D13: 人 | J13: 0.25 | K13: 0.25 | Q13: =SUM(E13:P13)*49.9849 -> 24.99245 | R13: =Q13+Q14 -> 24.99245
D14: 費 | Q14: =SUM(E14:P14) -> 0 | R14: =R13/F106 -> 0.0066433026
C15: A6出席研討會並收集本分項計畫有關之訊息6/10 | D15: 人 | O15: 0.25 | P15: 0.25 | Q15: =SUM(E15:P15)*49.849 -> 24.9245 | R15: =Q15+Q16 -> 24.9245
D16: 費 | Q16: =SUM(E16:P16) -> 0 | R16: =R15/F106 -> 0.0066252407
C17: 合計人月 | E17: =E5+E7+E9+E11+E13+E15 -> 0.5 | F17: =F5+F7+F9+F11+F13+F15 -> 0.9 | G17: =G5+G7+G9+G11+G13+G15 -> 0.9 | H17: =H5+H7+H9+H11+H13+H15 -> 0.9 | I17: =I5+I7+I9+I11+I13+I15 -> 0.65 | J17: =J5+J7+J9+J11+J13+J15 -> 0.9 | K17: =K5+K7+K9+K11+K13+K15 -> 0.65 | L17: =L5+L7+L9+L11+L13+L15 -> 0.4 | ... P17: =P5+P7+P9+P11+P13+P15 -> 0.75 | Q17: =SUM(E17:P17) -> 8
C18: 合計薪資 | E18: =E17*49.849 -> 24.9245 | F18: =F17*49.849 -> 44.8641 | G18: =G17*49.849 -> 44.8641 | H18: =H17*49.849 -> 44.8641 | I18: =I17*49.849 -> 32.40185 | J18: =J17*49.849 -> 44.8641 | K18: =K17*49.849 -> 32.40185 | L18: =L17*49.849 -> 19.9396 | ... Q18: =Q17*49.849 -> 398.792 | S18: 113年度 | T18: =SUM(E18:J19) -> 1366.7828
C19: 非屬薪資 | E19: =E6+E8+E10+E12+E14+E16 -> 500 | F19: =F6+F8+F10+F12+F14+F16 -> 26 | G19: =G6+G8+G10+G12+G14+G16 -> 26 | H19: =H6+H8+H10+H12+H14+H16 -> 26 | I19: =I6+I8+I10+I12+I14+I16 -> 26 | J19: =J6+J8+J10+J12+J14+J16 -> 526 | K19: =K6+K8+K10+K12+K14+K16 -> 26 | L19: =L6+L8+L10+L12+L14+L16 -> 26 | ... Q19: =Q6+Q8+Q10+Q12+Q14+Q16 -> 1260 | S19: 114年度 | T19: =SUM(K18:P19) -> 292.00925
C20: 費用小計 | E20: =SUM(E18:E19) -> 524.9245 | F20: =SUM(F18:F19) -> 70.8641 | G20: =SUM(G18:G19) -> 70.8641 | H20: =SUM(H18:H19) -> 70.8641 | I20: =SUM(I18:I19) -> 58.40185 | J20: =SUM(J18:J19) -> 570.8641 | K20: =SUM(K18:K19) -> 58.40185 | L20: =SUM(L18:L19) -> 45.9396 | ... O20: =SUM(O18:O19) -> 58.40185 | P20: 分項合計 | Q20: =SUM(Q18:Q19) -> 1658.792 | T20: =T18+T19 -> 1658.792
B22: 計畫項目 | C22: =人事費!A9 -> 3.蔣明諺 | E22: 7月 | F22: 8月 | G22: 9月 | H22: 10月 | I22: 11月 | J22: 12月 | K22: 1月 | L22: 2月 | M22: 3月 | N22: 4月 | O22: 5月 | P22: 6月
C23: B分項計畫 物業安全中心設置 | R23: 細項小計及權重
C24: B1物業管理及保全協力廠商探詢及轄內物業管理8/1 | D24: 人 | E24: 0.25 | F24: 0.5 | G24: 0.25 | Q24: =SUM(E24:P24)*人事費!E9/1000 -> 43.84 | R24: =Q24+Q25 -> 43.84
D25: 費 | Q25: =SUM(E25:P25) -> 0 | R25: =R24/F106 -> 0.011653215
C26: B2分析各管委會及承攬物業資訊製作物業資訊庫10/1 | D26: 人 | E26: 0.25 | G26: 0.25 | Q26: =SUM(E26:P26)*人事費!E9/1000 -> 21.92 | R26: =Q26+Q27 -> 21.92
D27: 費 | Q27: =SUM(E27:P27) -> 0 | R27: =R26/F106 -> 0.0058266074
C28: B3選定5家測試合作業物業並前往洽談合作事宜10/15 | D28: 人 | G28: 0.25 | H28: 0.25 | Q28: =SUM(E28:P28)*人事費!E9/1000 -> 21.92 | R28: =Q28+Q29 -> 21.92
D29: 費 | Q29: =SUM(E29:P29) -> 0 | R29: =R28/F106 -> 0.0058266074
C30: B4進行全區域的物業拜訪開拓創新社區安全網業務11/1 | D30: 人 | I30: 0.25 | J30: 0.25 | K30: 0.25 | L30: 0.25 | M30: 0.25 | N30: 0.25 | O30: 0.25 | P30: 0.25 | Q30: =SUM(E30:P30)*人事費!E9/1000 -> 87.68 | R30: =Q30+Q27 -> 87.68
D31: 費 | Q31: =SUM(E31:P31) -> 0 | R31: =R30/F106 -> 0.02330643
C32: B5完成全區域內物業分析報告及擬定安保顧問企劃3/11 | D32: 人 | L32: 0.25 | M32: 0.25 | Q32: =SUM(E32:P32)*人事費!E9/1000 -> 21.92 | R32: =Q32+Q86 -> 21.92
D33: 費 | Q33: =SUM(E33:P33) -> 0 | R33: =R32/F106 -> 0.0058266074
C34: B6出席研討會並收集本分項計畫有關之訊息6/10 | D34: 人 | O34: 0.25 | P34: 0.25 | Q34: =SUM(E34:P34)*人事費!E9/1000 -> 21.92 | R34: =Q34+Q35 -> 21.92
D35: 費 | Q35: =SUM(E35:P35) -> 0 | R35: =R34/F106 -> 0.0058266074
C36: 合計人月 | E36: =E24+E26+E28+E30+E32+E34 -> 0.5 | F36: =F24+F26+F28+F30+F32+F34 -> 0.5 | G36: =G24+G26+G28+G30+G32+G34 -> 0.75 | H36: =H24+H26+H28+H30+H32+H34 -> 0.25 | I36: =I24+I26+I28+I30+I32+I34 -> 0.25 | J36: =J24+J26+J28+J30+J32+J34 -> 0.25 | K36: =K24+K26+K28+K30+K32+K34 -> 0.25 | L36: =L24+L26+L28+L30+L32+L34 -> 0.5 | ... P36: =P24+P26+P28+P30+P32+P34 -> 0.5 | Q36: =SUM(E36:P36) -> 5
C37: 合計薪資 | E37: =E36*人事費!E9/1000 -> 21.92 | F37: =F36*人事費!E9/1000 -> 21.92 | G37: =G36*人事費!E9/1000 -> 32.88 | H37: =H36*人事費!E9/1000 -> 10.96 | I37: =I36*人事費!E9/1000 -> 10.96 | J37: =J36*人事費!E9/1000 -> 10.96 | K37: =K36*人事費!E9/1000 -> 10.96 | L37: =L36*人事費!E9/1000 -> 21.92 | M37: =N36*人事費!E9/1000 -> 10.96 | N37: =N36*人事費!E9/1000 -> 10.96 | O37: =O36*人事費!E9/1000 -> 21.92 | P37: =P36*人事費!E9/1000 -> 21.92 | Q37: =Q36*人事費!E9/1000 -> 219.2 | S37: 113年度 | T37: =SUM(E37:K38) -> 120.56
C38: 非屬薪資 | E38: =E25+E27+E29+E31+E33+E35 -> 0 | F38: =F25+F27+F29+F31+F33+F35 -> 0 | G38: =G25+G27+G29+G31+G33+G35 -> 0 | H38: =H25+H27+H29+H31+H33+H35 -> 0 | I38: =I25+I27+I29+I31+I33+I35 -> 0 | J38: =J25+J27+J29+J31+J33+J35 -> 0 | K38: =K25+K27+K29+K31+K33+K35 -> 0 | L38: =L25+L27+L29+L31+L33+L35 -> 0 | ... Q38: =Q25+Q27+Q29+Q31+Q33+Q35 -> 0 | S38: 114年度 | T38: =SUM(K37:P38) -> 98.64
C39: 費用小計 | E39: =SUM(E37:E38) -> 21.92 | F39: =SUM(F37:F38) -> 21.92 | G39: =SUM(G37:G38) -> 32.88 | H39: =SUM(H37:H38) -> 10.96 | I39: =SUM(I37:I38) -> 10.96 | J39: =SUM(J37:J38) -> 10.96 | K39: =SUM(K37:K38) -> 10.96 | L39: =SUM(L37:L38) -> 21.92 | ... O39: =SUM(O37:O38) -> 21.92 | P39: 分項合計 | Q39: =SUM(Q37:Q38) -> 219.2 | T39: =T37+T38 -> 219.2
B41: 計畫項目 | C41: =人事費!A11 -> 5.李道翔 | E41: 7月 | F41: 8月 | G41: 9月 | H41: 10月 | I41: 11月 | J41: 12月 | K41: 1月 | L41: 2月 | M41: 3月 | N41: 4月 | O41: 5月 | P41: 6月
C42: C分項計畫 資訊、勞務系統開發 | R42: 細項小計及權重
C43: C1 AI智慧社區服務系統及及無人保全開發商123招攬及合約簽訂7/30 | D43: 人 | E43: 0.5 | Q43: =SUM(E43:P43)*40 -> 20 | R43: =Q43+Q44 -> 520
D44: 費 | E44: 100 | F44: 30 | G44: 30 | H44: 30 | I44: 30 | J44: 30 | K44: 30 | L44: 30 | M44: 30 | N44: 30 | O44: 30 | P44: 100 | Q44: =SUM(E44:P44) -> 500 | R44: =R43/F106 -> 0.13822244
C45: C2 AI智慧社區服務系統完成商業及物業系統開發。9/1 | D45: 人 | F45: 0.25 | G45: 0.25 | Q45: =SUM(E45:P45)*40 -> 20 | R45: =Q45+Q46 -> 20
D46: 費 | Q46: =SUM(E46:P46) -> 0 | R46: =R45/F106 -> 0.0053162476
C47: C3 AI智慧社區服務系統完成社區專勤隊串接10/1 | D47: 人 | H47: 0.5 | Q47: =SUM(F47:P47)*40 -> 20 | R47: =Q47+Q48 -> 20
D48: 費 | Q48: =SUM(E48:P48) -> 0 | R48: =R47/F106 -> 0.0053162476
C49: C4 AI智慧社區服務系統、無人保全系統及完成串接10/1 | D49: 人 | E49: 0.25 | G49: 0.25 | Q49: =SUM(E49:P49)*40 -> 20 | R49: =Q49+Q46 -> 20
D50: 費 | Q50: =SUM(E50:P50) -> 0 | R50: =R49/F106 -> 0.0053162476
C51: C5各使用端意見收集及系統改善項目表提出1/15 | D51: 人 | G51: 0.1 | H51: 0.1 | I51: 0.1 | J51: 0.1 | K51: 0.1 | Q51: =SUM(E51:P51)*人事費!E10/1000 -> 20.92 | R51: =Q51+Q105 -> 20.92
D52: 費 | Q52: =SUM(E52:P52) -> 0 | R52: =R51/F106 -> 0.005560795
C53: C6出席研討會並收集本分項計畫有關之訊息6/10 | D53: 人 | O53: 0.25 | P53: 0.25 | Q53: =SUM(E53:P53)*人事費!E10/1000 -> 20.92 | R53: =Q53+Q54 -> 20.92
D54: 費 | Q54: =SUM(E54:P54) -> 0 | R54: =R53/F106 -> 0.005560795
C55: 合計人月 | E55: =E43+E45+E47+E49+E51+E53 -> 0.75 | F55: =F43+F45+F47+F49+F51+F53 -> 0.25 | G55: =G43+G45+G47+G49+G51+G53 -> 0.6 | H55: =H43+H45+H47+H49+H51+H53 -> 0.6 | I55: =I43+I45+I47+I49+I51+I53 -> 0.1 | J55: =J43+J45+J47+J49+J51+J53 -> 0.1 | K55: =K43+K45+K47+K49+K51+K53 -> 0.1 | L55: =L43+L45+L47+L49+L51+L53 -> 0 | ... P55: =P43+P45+P47+P49+P51+P53 -> 0.25 | Q55: =SUM(E55:P55) -> 3
C56: 合計薪資 | E56: =E55*人事費!E10/1000 -> 31.38 | F56: =F55*41.84 -> 10.46 | G56: =G55*41.84 -> 25.104 | H56: =H55*41.84 -> 25.104 | I56: =I55*41.84 -> 4.184 | J56: =J55*41.84 -> 4.184 | K56: =K55*41.84 -> 4.184 | L56: =L55*41.84 -> 0 | M56: =M55*41.84 -> 0 | ... Q56: =Q55*41.84 -> 125.52 | S56: 113年度 | T56: =SUM(E56:J57) -> 350.416
C57: 非屬薪資 | E57: =E44+E46+E48+E50+E52+E54 -> 100 | F57: =F44+F46+F48+F50+F52+F54 -> 30 | G57: =G44+G46+G48+G50+G52+G54 -> 30 | H57: =H44+H46+H48+H50+H52+H54 -> 30 | I57: =I44+I46+I48+I50+I52+I54 -> 30 | J57: =J44+J46+J48+J50+J52+J54 -> 30 | K57: =K44+K46+K48+K50+K52+K54 -> 30 | L57: =L44+L46+L48+L50+L52+L54 -> 30 | ... Q57: =Q44+Q46+Q48+Q50+Q52+Q54 -> 500 | S57: 114年度 | T57: =SUM(K56:P57) -> 275.104
C58: 費用小計 | E58: =SUM(E56:E57) -> 131.38 | F58: =SUM(F56:F57) -> 40.46 | G58: =SUM(G56:G57) -> 55.104 | H58: =SUM(H56:H57) -> 55.104 | I58: =SUM(I56:I57) -> 34.184 | J58: =SUM(J56:J57) -> 34.184 | K58: =SUM(K56:K57) -> 34.184 | L58: =SUM(L56:L57) -> 30 | ... O58: =SUM(O56:O57) -> 40.46 | P58: 分項合計 | Q58: =SUM(Q56:Q57) -> 625.52
B60: 計畫項目 | C60: =人事費!A10 -> 4.林詩妘 | E60: 7月 | F60: 8月 | G60: 9月 | H60: 10月 | I60: 11月 | J60: 12月 | K60: 1月 | L60: 2月 | M60: 3月 | N60: 4月 | O60: 5月 | P60: 6月
C61: D分項計畫 各分项計畫串接結合及驗證控管 | R61: 細項小計及權重
C62: D1營運中心空間規劃建構，直營咖啡廳SOP制定8/30 | D62: 人 | E62: 0.25 | F62: 0.25 | Q62: =SUM(E62:P62)*人事費!E10/1000 -> 20.92 | R62: =Q62+Q63 -> 20.92
D63: 費 | Q63: =SUM(E63:P63) -> 0 | R63: =Q63+Q64 -> 20.92
C64: D2 機動保全、特勤保全、定點保全狀況個突發狀態默契訓練及SOP制定及驗證9/10、12/10、6/10 | D64: 人 | G64: 0.2 | J64: 0.2 | P64: 0.1 | Q64: =SUM(E64:P64)*人事費!E10/1000 -> 20.92 | R64: =Q64+Q65 -> 170.32
D65: 費 | G65: =J65 -> 49.8 | J65: =P65 -> 49.8 | P65: =文字計畫資訊!I730 -> 49.8 | Q65: =SUM(E65:P65) -> 149.4 | R65: =Q65+Q66 -> 170.32
C66: D3串接雲端點餐系統執行單店服務量能測試9/1、10/1、11/1 | D66: 人 | G66: 0.2 | H66: 0.2 | I66: 0.1 | Q66: =SUM(F66:P66)*人事費!E10/1000 -> 20.92 | R66: =Q66+Q67 -> 176.32
D67: 費 | G67: 51.8 | H67: 51.8 | I67: 51.8 | Q67: =SUM(E67:P67) -> 155.4 | R67: =R66/F106 -> 0.046868039
C68: D3串接雲端點餐系統執行聯合銷售服務量能測9/1、11/1 1/01 | D68: 人 | I68: 0.2 | K68: 0.1 | P68: 0.2 | Q68: =SUM(F68:P68)*人事費!E10/1000 -> 20.92 | R68: =Q68+Q65 -> 170.32
D69: 費 | I69: =文字計畫資訊!I763 -> 63.8 | K69: =文字計畫資訊!I763 -> 63.8 | P69: =文字計畫資訊!I763 -> 63.8 | Q69: =SUM(E69:P69) -> 191.4 | R69: =R68/F106 -> 0.045273165
C70: D5 AI智慧社區服務系統上限驗證1/15 | D70: 人 | J70: 0.3 | K70: 0.3 | L70: 0.4 | Q70: =SUM(F70:P70)*40 -> 40 | R70: =Q70+Q71 -> 108
D71: 費 | K71: 34 | L71: 34 | Q71: =SUM(E71:P71) -> 68 | R71: =R70/F106 -> 0.028707737
C72: D6出席研討會並收集本分項計畫有關之訊息6/10 | D72: 人 | O72: 0.25 | P72: 0.25 | Q72: =SUM(F72:P72)*人事費!E10/1000 -> 20.92 | R72: =Q72+Q73 -> 20.92
D73: 費 | Q73: =SUM(E73:P73) -> 0 | R73: =R72/F106 -> 0.005560795
C74: 合計人月 | E74: =E62+E64+E66+E68+E70+E72 -> 0.25 | F74: =F62+F64+F66+F68+F70+F72 -> 0.25 | G74: =G62+G64+G66+G68+G70+G72 -> 0.4 | H74: =H62+H64+H66+H68+H70+H72 -> 0.2 | I74: =I62+I64+I66+I68+I70+I72 -> 0.3 | J74: =J62+J64+J66+J68+J70+J72 -> 0.5 | K74: =K62+K64+K66+K68+K70+K72 -> 0.4 | L74: =L62+L64+L66+L68+L70+L72 -> 0.4 | ... P74: =P62+P64+P66+P68+P70+P72 -> 0.55 | Q74: =SUM(E74:P74) -> 3.5
C75: 合計薪資 | E75: =E74*人事費!E10/1000 -> 10.46 | F75: =F74*人事費!E10/1000 -> 10.46 | G75: =G74*人事費!E10/1000 -> 16.736 | H75: =H74*人事費!E10/1000 -> 8.368 | I75: =I74*人事費!E10/1000 -> 12.552 | J75: =J74*人事費!E10/1000 -> 20.92 | K75: =K74*人事費!E10/1000 -> 16.736 | L75: =L74*人事費!E10/1000 -> 16.736 | M75: =M74*人事費!B10/1000 -> 0 | N75: =N74*人事費!E10/1000 -> 0 | O75: =O74*人事費!E10/1000 -> 10.46 | P75: =P74*人事費!E10/1000 -> 23.012 | Q75: =Q74*人事費!E10/1000 -> 146.44 | S75: 113年度 | T75: =SUM(E75:J76) -> 398.296
C76: 非屬薪資 | E76: =E63+E65+E67+E69+E71+E73 -> 0 | F76: =F63+F65+F67+F69+F71+F73 -> 0 | G76: =G63+G65+G67+G69+G71+G73 -> 101.6 | H76: =H63+H65+H67+H69+H71+H73 -> 51.8 | I76: =I63+I65+I67+I69+I71+I73 -> 115.6 | J76: =J63+J65+J67+J69+J71+J73 -> 49.8 | K76: =K63+K65+K67+K69+K71+K73 -> 97.8 | L76: =L63+L65+L67+L69+L71+L73 -> 34 | ... Q76: =Q63+Q65+Q67+Q69+Q71+Q73 -> 564.2 | S76: 114年度 | T76: =SUM(K75:P76) -> 312.344
C77: 費用小計 | E77: =SUM(E75:E76) -> 10.46 | F77: =SUM(F75:F76) -> 10.46 | G77: =SUM(G75:G76) -> 118.336 | H77: =SUM(H75:H76) -> 60.168 | I77: =SUM(I75:I76) -> 128.152 | J77: =SUM(J75:J76) -> 70.72 | K77: =SUM(K75:K76) -> 114.536 | L77: =SUM(L75:L76) -> 50.736 | ... Q77: =SUM(Q75:Q76) -> 710.64 | R77: 分項合計 | T77: =T76+T75 -> 710.64
B79: 計畫項目 | C79: =人事費!A8 -> 2.江政隆 | E79: 7月 | F79: 8月 | G79: 9月 | H79: 10月 | I79: 11月 | J79: 12月 | K79: 1月 | L79: 2月 | M79: 3月 | N79: 4月 | O79: 5月 | P79: 6月
C80: E分項計畫 計畫管考設備採購暨友善勞動制度及產業需求研發 | R80: 細項小計及權重
C81: E1本計畫各項新購設備使用費7/1 | D81: 人 | Q81: =SUM(F81:P81)*40 -> 0 | R81: =Q81+Q82 -> 147.38
D82: 費 | E82: =文字計畫資訊!D822/60*12 -> 76.08 | G82: =文字計畫資訊!I822/60*12 -> 71.3 | Q82: =SUM(E82:P82) -> 147.38 | R82: =R81/F106 -> 0.039175429
C83: E2顧問選任聘用，協助社區發展協會開發社區專勤隊9/1 | D83: 人 | E83: 0.4 | F83: 0.3 | G83: 0.3 | Q83: =SUM(E83:P83)*人事費!E8/1000 -> 46.84 | R83: =Q83+Q84 -> 306.84
D84: 費 | E84: 30 | F84: 30 | G84: 20 | H84: 20 | I84: 20 | J84: 20 | K84: 20 | L84: 20 | M84: 20 | N84: 20 | O84: 20 | P84: 20 | Q84: =SUM(E84:P84) -> 260 | R84: =R83/F106 -> 0.081561871
C85: E3計畫進度管考及協調指、各計畫開發研發工作職務代理ALLTIME | D85: 人 | G85: 0.1 | H85: 0.1 | I85: 0.1 | J85: 0.1 | K85: 0.1 | L85: 0.1 | M85: 0.1 | N85: 0.1 | O85: 0.1 | P85: 0.1 | Q85: =SUM(F85:P85)*人事費!E8/1000 -> 46.84 | R85: =Q85+Q86 -> 46.84
D86: 費 | Q86: =SUM(E86:P86) -> 0 | R86: =R85/F106 -> 0.012450652
C87: E4辦理產官學民四方專案研討會6/10 | D87: 人 | O87: 0.5 | P87: 0.5 | Q87: =SUM(F87:P87)*人事費!E8/1000 -> 46.84 | R87: =Q87+Q88 -> 46.84
D88: 費 | Q88: =SUM(E88:P88) -> 0 | R88: =R87/F106 -> 0.012450652
D89: 人 | Q89: =SUM(F89:P89)*40 -> 0
D90: 費 | Q90: =SUM(E90:P90) -> 0
D91: 人 | Q91: =SUM(F91:P91)*40 -> 0
D92: 費 | Q92: =SUM(E92:P92) -> 0
C93: 合計人月 | E93: =E81+E83+E85+E87+E89+E91 -> 0.4 | F93: =F81+F83+F85+F87+F89+F91 -> 0.3 | G93: =G81+G83+G85+G87+G89+G91 -> 0.4 | H93: =H81+H83+H85+H87+H89+H91 -> 0.1 | I93: =I81+I83+I85+I87+I89+I91 -> 0.1 | J93: =J81+J83+J85+J87+J89+J91 -> 0.1 | K93: =K81+K83+K85+K87+K89+K91 -> 0.1 | L93: =L81+L83+L85+L87+L89+L91 -> 0.1 | ... P93: =P81+P83+P85+P87+P89+P91 -> 0.6 | Q93: =SUM(E93:P93) -> 3
C94: 合計薪資 | E94: =E93*46.84 -> 18.736 | F94: =F93*46.84 -> 14.052 | G94: =G93*46.84 -> 18.736 | H94: =H93*46.84 -> 4.684 | I94: =I93*46.84 -> 4.684 | J94: =J93*46.84 -> 4.684 | K94: =K93*46.84 -> 4.684 | L94: =L93*46.84 -> 4.684 | ... Q94: =Q93*46.84 -> 140.52 | S94: 113年度 | T94: =SUM(E94:J95) -> 352.956
C95: 非屬薪資 | E95: =E82+E84+E86+E88+E90+E92 -> 106.08 | F95: =F82+F84+F86+F88+F90+F92 -> 30 | G95: =G82+G84+G86+G88+G90+G92 -> 91.3 | H95: =H82+H84+H86+H88+H90+H92 -> 20 | I95: =I82+I84+I86+I88+I90+I92 -> 20 | J95: =J82+J84+J86+J88+J90+J92 -> 20 | K95: =K82+K84+K86+K88+K90+K92 -> 20 | L95: =L82+L84+L86+L88+L90+L92 -> 20 | ... Q95: =Q82+Q84+Q86+Q88+Q90+Q92 -> 407.38 | S95: 114年度 | T95: =SUM(K96:P96) -> 194.944
C96: 費用小計 | E96: =SUM(E94:E95) -> 124.816 | F96: =SUM(F94:F95) -> 44.052 | G96: =SUM(G94:G95) -> 110.036 | H96: =SUM(H94:H95) -> 24.684 | I96: =SUM(I94:I95) -> 24.684 | J96: =SUM(J94:J95) -> 24.684 | K96: =SUM(K94:K95) -> 24.684 | L96: =SUM(L94:L95) -> 24.684 | ... Q96: =SUM(Q94:Q95) -> 547.9 | R96: 分項合計 | T96: =T94+T95 -> 547.9
D98: 研發計畫所需費用 | E98: 勞務委外費 | F98: =SUM(F8:O8) -> 260 | I98: 各分項計畫權重 | L98: 經費使用年度
E99: 研發設備使用 | F99: =SUM(E82+F82+G82) -> 147.38 | I99: =C4 -> A分項計畫 商業資訊中心設置計畫 | J99: =Q20 -> 1658.792 | L99: 113年度 | M99: 114年度
E100: 委託開發 | F100: =SUM(E44:P44) -> 500 | I100: =C23 -> B分項計畫 物業安全中心設置 | J100: =Q39 -> 219.2 | L100: =T18+T37+T56+T75+T94 -> 2589.0107 | M100: =T19+T38+T57+T76+T95 -> 1173.0412
E101: 技術引進 | F101: =E6+J6 -> 1000 | I101: =C42 -> C分項計畫 資訊、勞務系統開發 | J101: =Q58 -> 625.52 | L101: =L100/J104*100% -> 0.68819111 | M101: =M100/J104 -> 0.31180889
E102: 驗證費用 | F102: =G65+J65+P65+G67+H67+I67+I69+K69+P69+K71+L71 -> 564.2 | I102: =C61 -> D分項計畫 各分项計畫串接結合及驗證控管 | J102: =Q77 -> 710.64 | Q102: 新購研發設備 | T102: =文字計畫資訊!I823 -> 736.9
E103: 顧問費用 | F103: =SUM(G84:P84) -> 200 | I103: =C80 -> E分項計畫 計畫管考設備採購暨友善勞動制度及產業需求研發 | J103: =Q96 -> 547.9 | Q103: 營運中心租用租金 | T103: =40000*12/1000 -> 480
E104: 其他費用 | F104: =E84+F84 -> 60 | I104: 總經費 | J104: =SUM(J99:J103) -> 3762.052 | Q104: 公司實際人事費用合計 | T104: =SUM(人事費!E7:E12)*111%*12/1000 -> 2999.664
E105: 人事費用 | F105: =Q94+Q75+Q56+Q37+Q18 -> 1030.472
...

Sheet 文字計畫資訊
F2: 限閱文件
B3: 經濟部科技研究發展專案
B5: 產業升級創新平台輔導計畫(新興育成)
B8: 運用AI智能系統整合勞務產能有效降低物業(商業)安全維護(聯合雲端銷售)成本並提高服務品質開發計畫(草 案)
B15: 計畫期間：自113 年 7月 1日至 114年 7 月 1 日止
B22: 公司名稱：五常物業規劃管理顧問股份有限公司
B23: 計畫管理單位：財團法人台灣中小企業聯合輔導基金會
B26: 中 華 民 國113年 4月
D29: 運用AI智能系統整合勞務產能有效降低物業(商業)安全維護(聯合雲端銷售)成本並提高服務品質開發計畫︵草案︶ 公司名稱 五常物業規劃顧問股份有限公司
A73: 計劃書摘要表
B74: 綜合資料
F75: 金額單位：千元
A76: 計畫名稱 | C76: 運用AI智能系統整合勞務產能有效降低物業(商業)安全維護(聯合雲端銷售)成本並提高服務品質開發計畫
A77: 公司名稱 | C77: 五常物業管理規劃顧問股份有限公司 | F77: 通訊地址：24151新北市三重區五常里28鄰仁義街161號1樓
A78: 法人名稱 | C78: 新北市三重區五常社區發展協會 | F78: 通訊地址：24151新北市三重區五常里28鄰仁義街161號1樓
A79: 計畫起～訖時間 | C79: 113年7月1日～114年7月1日 （共12個月）
A80: 計畫主持人 | C80: 姓名 | D80: 江政隆 | F80: 電話 | I80: (02)29866856
C81: 職稱 | D81: 營運長 | F81: 電子信箱 | I81: wuchang1100606355@gmail.com
A82: 協同計畫主持人 | C82: 姓名 | D82: 林詩妘 | F82: 電話 | I82: 907565121
C83: 職稱 | D83: 協理 | F83: 電子信箱
A84: 年度經費 | C84: 政 府 | E84: 公 司 | H84: 計 畫
C85: 補助款 | E85: 自籌款 | H85: 總經費
A86: 113年度 | C86: =H86-E86 -> 1165.0548 | E86: =H86*0.55 -> 1423.9559 | H86: =計畫架構圖表!L100 -> 2589.0107
C87: (法人)
A88: 114年度 | C88: =H88-E88 -> 410.56444 | E88: =H88*65% -> 762.47681 | H88: =計畫架構圖表!M100 -> 1173.0412
C89: (法人)
A90: ＸＸ年度 | C90: (公司)
C91: (法人)
A92: 合 計
A93: 占 總 經 | C93: 0.45 | E93: 0.55 | H93: 1
A94: 費 比 重%
A95: 計畫聯絡人 | C95: 姓名 | D95: 周誼芬 | F95: 電話 | I95: (02)29866856
C96: 職稱 | D96: 財務協理 | F96: 電子信箱
A97: 一、公司簡介
B98: (一)公司名稱：五常物業管理規劃顧問股份有限公司
B99: (二)核准設立日期：113年 月 日
B100: (三)代表人：阮氏泉
B101: (四)主要營業項目：
B102: 物業及商業管理規劃顧問業、法人或公司行政業務承攬業、餐飲服務及加工業、物業管理或商業經營衍生服務產業、區域健康照護業務規劃業、廢棄物清理業、人力資源規劃業
A103: 二、產業與市場需求
B104: 1.新建案因規模小戶數不多，需要新型態的公寓大廈管理維護承攬服務。
B105: 2.仁義商圈餐飲業因巷弄狹小及人口大量移入交通癱瘓，需要新型態的商會服務。
B106: 3.公益組織因都會化社區聯繫不易，無更多人力及資源辦理社區照護業務及會務，需資金及人力挹注進行會務行政協助。
B107: 三、創新服務開發說明
B108: 綜合都會區社區商業、物業需求、社區組織的需求(服務客群) ，以社區整體發展的高度及遠見，輔商業營運的組織及技術(技術優勢)，盤點各行業的營運需求，利用各產業提供的服務項目(盤點分析) ，利用物業高密集度、商業高同質性、AI核心及雲端數位技術(環境優勢) ，結合社區安全、商業資訊、環保永續、健康照護四大功能中心營運網絡(核心機構) ，整合橫向業務、鏈結異業資源(新創方式)、研發創新制度(開發服務)，藉以達到降低營運成本【商業、物業、照護】、提高附加價值【環保、物業、照護】、延伸營運觸角【商業、照護、環保】、開發消費客群【商業、物業、照護】(計畫目的)
A109: 四、計畫執行優勢
B110: 營運組織形象清新：閉鎖型公司股東單純，社會企業共享營利(公益品牌競爭力)。
B111: 營運能力完整豐富：計畫主持人(本司營運長)各領域從業經驗豐富資歷證照完整，足以鏈接各產業服務供給及營運需求。(生產競爭力)
B112: 營運條件得天獨厚：重劃區開發第三年人口爆炸式成長，面臨物業承攬更換期(天時)、住商區畫分明確營運點位於交接處位置絕佳(地利) 在地發展協會社工員及弱勢族群注資成立，股東群在地居住40年，地方關係根深蒂固(人和)。(環境競爭力)
B113: 五、計畫結案後2年內預期效益 單位：千元
A114: 量化效益 | B114: 計畫效益 | C114: 項 目 | D114: N年 | F114: N+1年 | H114: N+2
C115: 營業淨利(單位：千/月) | D115: =營運財務規劃預測!E9/1000/12 -> 243.80036 | F115: 290(240+50) | H115: 380(280+100)
C116: 月毛利額(單位：千) | D116: =營運財務規劃預測!E9/1000/12 -> 243.80036 | F116: 20 | H116: 90
C117: 計畫年(X12)總毛利額(單位：千) | D117: =營運財務規劃預測!E9/1000 -> 2925.6043 | F117: 240 | H117: 1080
C118: 預估毛利率(%) | D118: 虧損 | F118: 0.069 | H118: 0.237
B119: 經濟效益 | C119: 行銷方式(OEM、ODM或自有品牌比重) | D119: 商業OEM、物業ODM | F119: 商業ODM、物業自有 照護OEM、環保自有 | H119: 全自有或財團法人化
C121: 預估市場占有率(%) | D121: 0.02 | F121: 0.04 | H121: 0.1
C122: 預計研發投資額 | D122: =計畫架構圖表!F106-計畫架構圖表!F99 -> 3614.672 | F122: 500 | H122: 500
C124: 預計設備投資額 | D124: =計畫架構圖表!T102 -> 736.9 | F124: 500 | H124: 500
C125: 降低生產成本(千元) | D125: 0 | F125: 300 | H125: 360
C126: 成果發表會(場)/人數 | D126: 9/2000 | F126: 1/1000 | H126: 1/2000
A128: 創新服務應用 | C128: 專利申請（件） | D128: 2
C129: 專利核准（件）
C130: 衍生新服務業務（項） | D130: 1項 | F130: 1項 | H130: 0項
A131: 社會效益 | C131: 累計增加就業人數 | D131: 1人 | F131: 5人 | H131: 10人
C132: 創業育成累計（家） | D132: 1 | F132: 1 | H132: 1
C133: 專案聘僱中高齡弱勢族群人數累計 | D133: 18人 | F133: 30人 | H133: 45人
A134: 學術成就 | C134: 辦理學術活動(累計場次) | D134: 1 | F134: 1 | H134: 1
C135: 研究報告（累計篇數） | D135: 1 | F135: 1 | H135: 2
A136: 質化效益 | C136: 透過整合社區運作所需要的功能設立營運中心服務區域內各業及非營利組織、導入雲端數位科技協助其升級，透過開發AI社區服務系統系統整合區域內的商業銷售、物業管理、社區照護、環境永續四項社區服務功能，並且對升級整合產業產生勞務需求進時間及功能的拆分重組工作將部分適合中高齡弱勢族群委託社區發展協會進行分配、需要體能及專業的部分由我司聘用管理、開發區域內經濟及勞動產能，以達成本司創辦的下列四個目標整合區域組織合作開發互助、導引消費方向提振區域經濟、創造服務需求媒介弱勢居民、共享共有共好宜居樂活社區
A139: 六、 | B139: 計畫關鍵字：區域服務中心、區域發展、同業共同發展、異業聯合銷售、創新物業服務
A141: 一、公司概況
A142: 一、基本資料
B143: 公司簡介
A144: (一) | B144: (一)
B145: 1.核准設立日期
B146: 2.114 年實收資本額：5,000 千元
B147: 3.代表人：阮氏泉
B150: (二) 主要股東及持股比例主要股東 | E150: 持有股份(每股10元)
B151: 江政隆(113年公司成立股東會通過，此股份在新北市五常社區發展協會會員大會通過並社團法人化後，所有權人江政隆可將此股份贈與該會) | E151: 100000江政隆勞務出資 | H151: 0.3
B153: (環保業務技術佔股，113年公司成立股東會通過此股份由所有權江政隆指定承購人) | E153: 10000 | H153: 0.0165
B155: (資訊業務技術佔股，113年公司成立股東會通過此股份由所有權江政隆指定承購人) | E155: 10000 | H155: 0.0165
B156: 江政隆 | E156: 107000 | H156: 0.045
B157: 江政隆實際占比小計 | E157: 227.000(100,000為勞務出資股) | H157: 0.378
B158: 阮氏泉 | E158: 180000 | H158: 0.3
B159: 林詩妘 | E159: 25000 | H159: 0.042
B160: 蔣明諺 | E160: 168000 | H160: 0.28
B161: 合計 | E161: 600000 | H161: 1
A163: (三)營運現況：
B164: 新開設公司，目前正待依本計畫規劃時程開啟營運，目前已擁有五常社區發展協會會務委託合約、常勝江山A區物業維護管理顧問合約共計新台幣五十六萬元整，本計畫所載之內容於專利認證審查期中。
A165: 金額單位：千元
B166: (四)產品及服務銷售方式
B167: 1.商業服務:由本司直營咖啡店採區域聯合營運的多元銷售模式、協助商圈商家利用本司所開發AI社區服務系統，串接線上預購功能、線上點餐及餐飲業離峰時間消費折讓等功能，對社區內居民的消費行為進行服務並具有消費行為導向的功能、為社區商圈整體的銷售行為規劃，並藉由合併及簡化的外送業務，大幅降低商業營運及消費者所需負擔的成本
B168: 2.勞務市場:利用AI智能系統，整合ERP及CRM繼LINE模組功能，提供社區內中高齡及弱勢族群合宜的額外工作機會，並由本司整合工序後的開發創新區域勞務工作需求，具有低勞動強度、高時間彈性等特質的工作項目，有效運用中高齡及弱勢族群的剩餘產能，利用物業及餐飲業的高密度，將大大降低耗費在交通上的時間成本，藉由創新的派遣制度，進行拆解後的短工時工作可以讓這些工作並不會成為主業，而是適合補充部分收入的兼職機會，讓更多需要的人受惠，使得此勞務派遣機制不會影響社區內的居民總獲利能力及來源使得此項派遣制度能夠提高社區居民的平均收入及消費能力並且本司安排具有照顧服務專長的照服員管理此項業務，以適合的勞務派遣工作，(外送、代班保全、巡邏保全、功能姓保全商業銷售峰期勞動力)開發具有彈性時間、低工作強度、以件計費的工作需求，在工作等待期間於備勤場所植入社區關懷據點的功能，發展創新的複合式中高齡照業及就業服務業務。
B169: 3.物業服務:了解物業不同階層客戶需求為做為開發業務之主要取向，透過拜訪了解實際需求後及本司在地的關係網，人脈，提供高機動性的服務及人力，如保全業的需求代班保全，無人保全系統搭配24H快速反應特勤保全、專業且高機動性的管理維護服務人員，公寓大廈管理條例諮詢、各類公寓大廈生活機能及服務提供設計，藉由提高物業的管理服務品質，將原本物業的定點保全人力資源藉由科技無人保全系統及社區安全網制度，有效的降低物業的成本並將降低的成本導向增進區域的生活機能及個人安全維護提升上。
A170: 二、經營團隊及執行能力
A171: (一) | B171: 全公司組織圖
A176: (二)全公司人力分析
B178: 職 別 | D178: 碩士 | F178: 學士 | H178: 專科
B179: 性別 | D179: 男 | E179: 女 | F179: 男 | G179: 女 | H179: 男 | I179: 女
...

Sheet 營運財務規劃預測
A1: 五常物業規劃股份有限公司營運預算書
A2: 借方統計表 單位：新台幣元
A3: 門 | B3: 款 | C3: 項 | D3: 科目 | E3: 第一年 | F3: 第二年 | G3: 備註
A4: 1 | B4: 1 | C4: 1 | D4: 商業收入 | E4: =2400000/2+90000 -> 1290000 | F4: =3000000+180000 -> 3180000 | G4: 按聊閣重新店經驗每月編列20萬元
D5: 商業顧問服務費 | E5: 0 | F5: =3000*3*12 -> 108000 | K5: 咖啡店
A6: 1 | B6: 1 | C6: 2 | D6: 物業及委託收入 | E6: =1200000/2 -> 600000 | F6: 1800000 | G6: 協會全年計畫規模約為200萬元，依合約收入20萬元 | K6: =E4-E30-E31-E39-E42-E51+120000 -> 512360.8
G7: 物業合約目前僅有1案全年36萬元 | K7: 初期成本
A8: 1 | B8: 2 | C8: 1 | D8: 補助收入 | E8: =計畫架構圖表!L100*1000*40% -> 1035604.3 | F8: =(計畫架構圖表!M100*40%*1000)+510000+200000 -> 1179216.5 | G8: SIIR計畫114年度餘額加上3.4萬X15=51萬元；及銀髮、婦女各10萬元業務費用 | K8: =E46+E47+E48-200000 -> 1006900
A9: 營業收入項小計 | E9: =SUM(E4:E8) -> 2925604.3 | F9: =SUM(F4:F8) -> 6267216.5
A10: 1 | B10: 2 | C10: 2 | D10: 其他收入 | G10: 不做預估 | K10: 政隆
A11: 1 | B11: 2 | C11: 3 | D11: 代收款項 | G11: 勞健保勞工負擔及勞退自提 | K11: 需出資額 | L11: 半年收益 | M11: 平均月收益
A12: 1 | B12: 2 | C12: 4 | D12: 孳息 | G12: 不做預估 | K12: =K8*60% -> 604140 | L12: =K6*60% -> 307416.48 | M12: =L12/6 -> 51236.08
D13: 資本公積
A14: 資本項目
A15: 3 | B15: 3 | C15: 1 | D15: 股本收入 | E15: 6000000 | G15: 一般股500,000股，面額10元 | K15: 明諺
G16: 特別股 100,000股，面額10元 | K16: 需出資額 | L16: 半年收益 | M16: 平均月收益
A17: 1 | B17: 4 | C17: 1 | D17: 永續發展基金(法定盈餘) | E17: 0 | G17: 不做預估
B18: 3 | C18: 3 | D18: 上期結餘 | E18: 0 | F18: =E70 -> 2069919 | G18: 不做預估 | K18: =60/0.4 -> 150
A19: 資本項小計 | E19: =SUM(E15:E18) -> 6000000 | F19: =SUM(F15:F18) -> 2069919
A20: 1 | B20: 4 | C20: 2 | D20: 勞工組織發展基金 | E20: 0 | F20: 0 | G20: 由勞工組織決定額度，本司提撥相同金額騎出暫定每名/月提撥500元，本項由盈餘勞工分配額提撥
A21: 1 | B21: 4 | C21: 3 | D21: 代管基金 | E21: 0 | F21: 0 | G21: 收託代管基金，如大樓管委會託管、五常社區發展基金
A22: 各類基金項小計 | E22: =SUM(E20:E21) -> 0 | F22: =SUM(F20:F21) -> 0
A23: 借方總計 | E23: =E9+E19+E22 -> 8925604.3 | F23: =F9+F19+F22 -> 8337135.5
A24: 貸方統計表 單位：新台幣元
A26: 2 | D26: 營業費用
A27: 2 | B27: 1 | D27: 人事費
A28: 2 | B28: 1 | C28: 1 | D28: 薪資支出A項 | E28: =SUM(人事費!B7:B12)*6 -> 835200 | F28: =SUM(人事費!B7:B12)*12 -> 1670400 | G28: 27,740*5
A29: 2 | B29: 1 | C29: 2 | D29: 薪資支出B項 | E29: =SUM(人事費!C7:C12)*6 -> 492000 | F29: =SUM(人事費!C7:C12)*12 -> 984000 | G29: 董事長20營運長18經理16協理14高等專員12初等專員10
A30: 2 | B30: 1 | C30: 3 | D30: 勞工保險費 | E30: =(E28+E29)*0.11*0.6 -> 87595.2 | F30: =(F28+F29)*0.11*0.6 -> 175190.4 | G30: 董事長1、營運長1、經理1、協理1、初專1
A31: 2 | B31: 1 | C31: 4 | D31: 勞工健保費 | E31: =(E28+E29)*0.02 -> 26544 | F31: =(F28+F29)*0.02 -> 53088 | G31: 董事長1、營運長1、經理1、協理1、初專1
A32: 2 | B32: 1 | C32: 5 | D32: 勞工組織費 | E32: 15000 | F32: 30000 | G32: 每人500
A33: 2 | B33: 1 | C33: 6 | D33: 勞工分紅及福利費用 | E33: 0 | F33: 0
A34: 2 | B34: 1 | C34: 7 | D34: 勞工教育訓練費 | E34: =計畫架構圖表!E84+計畫架構圖表!F84*1000 -> 30030 | F34: 80000
A35: 人事費用小計 | E35: =SUM(E28:E34) -> 1486369.2 | F35: =SUM(F28:F34) -> 2992678.4
A36: 2 | B36: 2 | D36: 辦公費
A37: 2 | B37: 2 | C37: 1 | D37: 辦公設備維護 | E37: =(E48-400000)*0.05 -> 16845 | F37: 20000 | G37: 筆電3X50K=150K,桌椅20K | M37: =365*500 -> 182500
B38: 2 | C38: 2 | D38: 行政耗材費 | E38: 5000 | F38: 5000 | G38: 文具、影印紙、文書器材
B39: 2 | C39: 3 | D39: 水電費 | E39: =12000*6 -> 72000 | F39: =12000*12 -> 144000 | G39: 每月1.2萬計
B40: 2 | C40: 4 | D40: 勞工副食費 | E40: =F40/2 -> 91250 | F40: =365*500 -> 182500 | G40: 每人每日100計，用餘歸直營商店營收
D41: 設備維護費 | E41: =E37*0.05/2 -> 421.125 | F41: =E37*0.05 -> 842.25
B42: 2 | C42: 5 | D42: 租金 | E42: =35000*6 -> 210000 | F42: =35000*12 -> 420000
A43: 辦公費小計 | E43: =SUM(E37:E42) -> 395516.12 | F43: =SUM(F37:F42) -> 772342.25
A44: 2 | B44: 3 | D44: 商業營運費用
A45: 2 | B45: 3 | D45: 營運中心開辦費(維護費)
A46: 2 | B46: 3 | C46: 1 | D46: 修繕費 | E46: 400000 | F46: 30000
A47: 2 | B47: 3 | C47: 2 | D47: 房屋押金 | E47: 70000 | F47: 0
A48: 2 | B48: 3 | C48: 3 | D48: 設備及技術採購費 | E48: =(文字計畫資訊!D822+文字計畫資訊!I822)*1000 -> 736900 | F48: 0
D49: 開辦費(維護費)小計 | E49: =SUM(E46:E48) -> 1206900 | F49: =SUM(F46:F48) -> 30000
A50: 2 | B50: 3 | D50: 營運費用 | G50: 咖啡機280,000+製冰機70,000+.磨豆機30,000+冰箱50,000,客桌椅30,000，技術及商標轉移220,000
A51: 2 | B51: 3 | C51: 4 | D51: 材料費 | E51: =E4*35%+50000 -> 501500 | F51: =F4*30% -> 954000 | G51: 依咖啡零售業成本架構推算材料成本約為35&故23+235約等於240萬x0.35=84萬常備存量以2個月為基準應屬合宜
A52: 2 | B52: 3 | C52: 6 | D52: 其他費用(含營運準備金) | E52: =SUM(營運財務規劃預測!E4)*0.03+50000 -> 88700 | F52: =F9*0.03 -> 188016.49 | G52: 本項含營運準備金5萬其他費用為營業額之3%
D53: 小計 | E53: =SUM(E51:E52) -> 590200 | F53: =SUM(F51:F52) -> 1142016.5
A54: 技術轉移費(營運成本) | E54: =E49+E53 -> 1797100 | F54: =F49+F53 -> 1172016.5
D55: 行銷暨功能驗證費
A56: 2 | B56: 4 | C56: 1 | D56: 驗證活動餐費 | E56: =計畫架構圖表!F102*1000 -> 564200 | F56: 100000
A57: 行銷暨功能驗證費小計 | E57: =SUM(E56:E56) -> 564200 | F57: =SUM(F56:F56) -> 100000
D58: 開發或勞務委外費用
A59: 2 | B59: 5 | C59: 1 | D59: AI智慧社區服務系統開發 | E59: =SUM(計畫架構圖表!E44:J44)*1000 -> 250000 | F59: 25000
A60: 2 | B60: 5 | C60: 2 | D60: 社區專勤隊勞務費用 | E60: =SUM(計畫架構圖表!E7:J7)*1000*40 -> 80000 | F60: 260000
A61: 2 | B61: 5 | C61: 3 | D61: 無人保全系統委託開發 | E61: 0 | F61: 10000
A62: 開發或勞務委外費用 | E62: =SUM(E59:E61) -> 330000 | F62: =SUM(F59:F61) -> 295000
A63: 2 | B63: 6 | D63: 無形資產
A64: 2 | B64: 5 | C64: 2 | D64: 專利權 | E64: 1000000 | F64: 0
A65: 2 | B65: 5 | C65: 2 | D65: 無形資產小計 | E65: 1000000 | F65: 0
D66: 稅金
D67: 加值型營業稅 | E67: =(E4+E6)*0.04 -> 75600 | F67: =(F4+F5+F6)*0.04 -> 203520
A68: 貸項合計 | E68: =E62+E57+E54+E43+E35+E49+E65+E67 -> 6855685.3 | F68: =F62+F57+F54+F43+F35+F67 -> 5535557.1
A69: 本期損益 | E69: =E9-E68 -> -3930081 | F69: =F9-F68 -> 731659.36
A70: 股利及業主權益 | E70: =E23-E68 -> 2069919 | F70: =F23-F68 -> 2801578.3

Sheet 人事費
A1: =計畫經費彙總表!A1 -> 五常物業規劃顧問股份(閉鎖型)有限公司
A2: SIIR計畫－計畫人員薪資計算表 (113年07月)
I3: 金額單位:元
A4: 傳票日期 | C4: 傳票編號
A5: 計畫人員姓 名 | B5: 本(底)薪 A | C5: 職務加給或 技術津貼 B | D5: 主管加給 C | E5: 月薪小計 D=A+B+C | F5: 投入比率 (註1) I | G5: 可列入本計畫之薪餉J=D*I | H5: 本計畫加班費 K | I5: 應計入本計畫薪資 L=J+K
A7: 1.阮氏泉 | B7: 27840 | C7: 20000 | D7: 2000 | E7: =SUM(B7:D7) -> 49840 | F7: =計畫架構圖表!E17 -> 0.5 | G7: =ROUND(E7*F7,0) -> 24920 | H7: =加班記錄!I5 -> 0 | I7: =SUM(G7:H7) -> 24920
A8: 2.江政隆 | B8: 27840 | C8: 18000 | D8: 1000 | E8: =SUM(B8:D8) -> 46840 | F8: =計畫架構圖表!E93 -> 0.4 | G8: =E8*F8 -> 18736 | H8: =加班記錄!I6 -> 0 | I8: =SUM(G8:H8) -> 18736
A9: 3.蔣明諺 | B9: 27840 | C9: 16000 | D9: 0 | E9: =SUM(B9:D9) -> 43840 | F9: =計畫架構圖表!E36 -> 0.5 | G9: =ROUND(E9*F9,0) -> 21920 | H9: =加班記錄!I7 -> 0 | I9: =SUM(G9:H9) -> 21920
A10: 4.林詩妘 | B10: 27840 | C10: 14000 | D10: 0 | E10: =SUM(B10:D10) -> 41840 | F10: =計畫架構圖表!E55 -> 0.75 | G10: =ROUND(E10*F10,0) -> 31380 | H10: =加班記錄!I8 -> 0 | I10: =SUM(G10:H10) -> 31380
A11: 5.李道翔 | B11: 27840 | C11: 14000 | D11: 1000 | E11: =SUM(B11:D11) -> 42840 | F11: =計畫架構圖表!E74 -> 0.25 | G11: =ROUND(E11*F11,0) -> 10710 | H11: =加班記錄!I9 -> 0 | I11: =SUM(G11:H11) -> 10710
D12: 0 | E12: =SUM(B12:D12) -> 0 | F12: =工時記錄表!AI10 -> 0 | G12: =ROUND(E12*F12,0) -> 0 | H12: =加班記錄!I10 -> 0 | I12: =SUM(G12:H12) -> 0
A13: 合 計 | B13: =SUM(B6:B12) -> 139200 | C13: =SUM(C7:C12) -> 82000 | D13: =SUM(D7:D12) -> 4000 | E13: =SUM(E7:E12) -> 225200 | F13: =SUM(F7:F12) -> 2.4 | G13: =SUM(G7:G12) -> 107666 | H13: =SUM(H7:H12) -> 0 | I13: =ROUND(SUM(I6:I12),0) -> 107666
A15: 註1：投入比率應與工時記錄表合計當月份一致。每月投入比率以1為上限。
A16: 註2：帳務查核時應備妥下列文件備查: 1.薪資清冊(內容包含：發放之薪資結構明細計算)
A17: 2.銀行轉帳記錄或印領清冊
A19: 計畫主持人: | E19: 主辦會計: | I19: 填表人：

Sheet 加班記錄
A1: =計畫經費彙總表!A1 -> 五常物業規劃顧問股份(閉鎖型)有限公司
A2: SIIR計畫人員加班記錄總表 (112年××月)
I3: 金額單位:元
A4: 計畫人員姓 名 | B4: 加班事由 | F4: 加班時數 | G4: 加班費計算公式 | I4: 本計畫之加班費 | J4: 計畫人員簽名
A5: =人事費!A7 -> 1.阮氏泉
A6: =人事費!A8 -> 2.江政隆
A7: =人事費!A9 -> 3.蔣明諺
A8: =人事費!A10 -> 4.林詩妘
A9: =人事費!A11 -> 5.李道翔
A10: =人事費!A12 -> 0
A11: 合 計 | I11: =ROUND(SUM(I5:I10),0) -> 0
A13: 計畫主持人: | D13: 主辦會計: | H13: 填表人：

Sheet 顧問
A1: =計畫經費彙總表!A1 -> 五常物業規劃顧問股份(閉鎖型)有限公司
A2: SIIR計畫－顧問費(113年6月)
E3: 金額單位:元
A4: 姓名 | B4: 傳票日期 | C4: 傳票編號 | D4: 摘要 | E4: 合 計
A6: 官釗鈱 | E6: 10000
A7: 官釗鈱 | E7: 10000
A8: 官釗鈱
A9: 官釗鈱
A10: 官釗鈱
A11: 官釗鈱
A12: 官釗鈱
A15: 合 計 | E15: =ROUND(SUM(E6:E14),0) -> 20000
A17: 註1：帳務查核時應備妥下列文件備查:1.領款收據（應書明受領事由、受領人名、地址、
A18: 身份證編號，由受領人簽名 或蓋章） 2.證明支付金額之文件(ex:銀行匯款單據)
A19: 註2：顧問任職單位同意函。
A21: 計畫主持人: | C21: 主辦會計: | E21: 填表人：

Sheet 工時記錄表
A1: =計畫經費彙總表!A1 -> 五常物業規劃顧問股份(閉鎖型)有限公司
A2: SIIR計畫工時記錄表(112年07月)
A3: 姓名 | B3: 1 | C3: 2 | D3: 3 | E3: 4 | F3: 5 | G3: 6 | H3: 7 | I3: 8 | J3: 9 | K3: 10 | L3: 11 | M3: 12 | N3: 13 | O3: 14 | P3: 15 | Q3: 16 | R3: 17 | S3: 18 | T3: 19 | U3: 20 | V3: 21 | W3: 22 | X3: 23 | Y3: 24 | Z3: 25 | AA3: 26 | AB3: 27 | AC3: 28 | AD3: 29 | AE3: 30 | AF3: 31 | AG3: 合計 | AH3: 正常工作時數 | AI3: 投入 比率 | AJ3: 簽名欄
A5: =人事費!A7 -> 1.阮氏泉 | AG5: =SUM(B5:AF5) -> 0 | AH5: 160 | AI5: =AG5/AH5 -> 0
A6: =人事費!A8 -> 2.江政隆 | AG6: =SUM(B6:AF6) -> 0 | AH6: 160 | AI6: =AG6/AH6 -> 0
A7: =人事費!A9 -> 3.蔣明諺 | AG7: =SUM(B7:AF7) -> 0 | AH7: 160 | AI7: =AG7/AH7 -> 0
A8: =人事費!A10 -> 4.林詩妘 | AG8: =SUM(B8:AF8) -> 0 | AH8: 160 | AI8: =AG8/AH8 -> 0
A9: =人事費!A11 -> 5.李道翔
A17: 合計 | B17: =SUM(B5:B16) -> 0 | C17: =SUM(C5:C16) -> 0 | D17: =SUM(D5:D16) -> 0 | E17: =SUM(E5:E16) -> 0 | F17: =SUM(F5:F16) -> 0 | G17: =SUM(G5:G16) -> 0 | H17: =SUM(H5:H16) -> 0 | I17: =SUM(I5:I16) -> 0 | ... AG17: =SUM(AG5:AG16) -> 0 | AI17: =SUM(AI5:AI16) -> 0
A19: 註1.請假不論事由，請假時數均不得列入本計畫投入工時計算。
A20: 註2.公司加班如另發加班費則上表所統計之工時不含加班時數；如採補休方式則加班時數應計入，補休時則視同請假處理。
A21: 註3.每月投入比率最高為1.00。
A22: 註4.請計畫人員確認工時記錄後於簽名欄位簽名
E24: 計畫主持人: | S24: 主辦會計: | AD24: 填表人：

Sheet 材料費
A1: =計畫經費彙總表!A1 -> 五常物業規劃顧問股份(閉鎖型)有限公司
A2: SIIR計畫－消耗性器材及原材料費(113年7月)
J3: 金額單位:元
A4: 傳票日期 | B4: 傳票號碼 | C4: 發票日期 (領料日期) | D4: 發票編號 (領料單號) | E4: 供應商 | F4: 發票品名 (註2) | G4: 對照計畫書所列項目 (註1) | H4: 數量 | I4: 單價(材料明細或分攤表) | J4: 金額 (不含營業稅)
A6: 113.7.1 | B6: 1120424002 | C6: 112.7.01 | D6: AA001 | E6: ×× | F6: 招牌咖啡豆 | G6: 咖啡豆 | H6: 5 | I6: 200 | J6: =I6*H6 -> 1000
A7: 113.7.1 | B7: 1120424002 | C7: 113.7.01 | D7: AB001 | E7: ×× | F7: 品黃奶精 | G7: 奶精 | H7: 1 | I7: 1130 | J7: =I7*H7 -> 1130
A8: 113.7.1 | B8: 1120424002 | C8: 113.7.01 | D8: AB002 | F8: 光泉鮮奶 | G8: 鮮奶 | H8: 20 | I8: 53 | J8: =I8*H8 -> 1060
A9: 113.7.1 | B9: 1120424002 | C9: 113.7.01 | D9: AC001 | F9: 冷杯S | G9: 外帶杯 | H9: 50 | I9: 2 | J9: =I9*H9 -> 100
A10: 113.7.1 | B10: 1120424002 | C10: 113.7.01 | D10: AC002 | F10: 冷杯M | G10: 外帶杯 | H10: 50 | I10: 2 | J10: =I10*H10 -> 100
A11: 113.7.1 | B11: 1120424002 | C11: 112.7.01 | D11: AC003 | F11: 冷杯L | G11: 外帶杯 | H11: 50 | I11: 2 | J11: =I11*H11 -> 100
A12: 113.7.1 | B12: 1120424002 | C12: 113.7.01 | D12: AC011 | F12: 熱杯S | G12: 外帶杯 | H12: 50 | I12: 2 | J12: =I12*H12 -> 100
A13: 113.7.1 | B13: 1120424002 | C13: 113.7.01 | D13: AC012 | F13: 熱杯M | G13: 外帶杯 | H13: 50 | I13: 2 | J13: =I13*H13 -> 100
A14: 113.7.1 | B14: 1120424002 | C14: 113.7.01 | D14: AC013 | F14: 熱杯L | G14: 外帶杯 | H14: 50 | I14: 2 | J14: =I14*H14 -> 100
J15: =I15*H15 -> 0
J16: =I16*H16 -> 0
J17: =I17*H17 -> 0
J18: =I18*H18 -> 0
J19: =I19*H19 -> 0
J20: =I20*H20 -> 0
J21: =I21*H21 -> 0
J22: =I22*H22 -> 0
J23: =I23*H23 -> 0
J24: =I24*H24 -> 0
J25: =I25*H25 -> 0
J26: =I26*H26 -> 0
A27: 合 計 | J27: =ROUND(SUM(J5:J26),0) -> 3790
A29: 註1：「對照計畫書所列項目」名稱需與計畫書所列之材料項目名稱一致。
A30: 註2：「發票品名」請依發票填寫所列項目。
A31: 註3：如屬公司共通性材料領用，發票日期、發票號碼請改填寫領料單日期、領料單號碼
A32: 註4：營業稅不得報支。
A33: 註5：辦公室所需之事務性耗材不得報支。
A34: 註6：帳務查核時應備妥下列文件備查:1.為專案計畫採購者應提供統一發票、收據或進口結匯單據與invoice、 及內部轉帳傳票、請購單、採購單
A35: 及驗收單足以證明之憑證。 2.自共通性器材領料應提供：領料單、材料明細帳或分攤表。3.涉及外幣支付時應附當時之外幣匯率表。
B37: 計畫主持人: | F37: 主辦會計: | I37: 填表人：

Sheet 設備使用費
A1: =計畫經費彙總表!A1 -> 五常物業規劃顧問股份(閉鎖型)有限公司
A2: SIIR計畫－設備使用費(1)---已有設備(112年××月)
K3: 金額單位:元
A4: 傳票日期 | C4: 傳票編號
A5: 財產編號 | B5: 設備名稱 | C5: 對照計畫書所列項目 | D5: 取得日期 | E5: 購入成本 (單套) | F5: 套數 A1 | G5: 投入時 單套帳面價值 （未折減餘額） A2 | H5: 剩餘使用月數 | I5: 每月攤提使用費 A3=A1*A2*/剩餘使用月數 (詳如註3) | J5: 本期投入比率 A4 | K5: 本期使用費 A5=A3*A4
A7: (1)1130001 | B7: 筆記型電腦 | C7: 筆記型電腦 | D7: 112.10.20 | E7: 80000 | F7: 1 | G7: 80000 | H7: 55 | I7: =IF(H7,G7/H7,0) -> 1454.5455 | J7: =設備使用記錄表!AJ6 -> 0.7 | K7: =ROUND(I7*J7,E83) -> 1018
A8: (1)1130002 | B8: 桌上型電腦 | C8: 桌上型電腦 | D8: 110.01.30 | E8: 35000 | F8: 1 | G8: 35000 | H8: 30 | I8: =IF(H8,G8/H8,0) -> 1166.6667 | J8: =設備使用記錄表!AJ7 -> 1 | K8: =ROUND(I8*J8,0) -> 1167
A9: (2)1130003 | B9: 電冰箱 | C9: 電冰箱 | D9: 110.07.25 | E9: 30000 | F9: 1 | G9: 30000 | H9: 30 | I9: =IF(H9,G9/H9,0) -> 1000 | J9: =設備使用記錄表!AJ8 -> 1 | K9: =ROUND(I9*J9,0) -> 1000
I10: =IF(H10,G10/H10,0) -> 0 | J10: =設備使用記錄表!AJ9 -> 0 | K10: =ROUND(I10*J10,0) -> 0
I11: =IF(H11,G11/H11,0) -> 0 | J11: =設備使用記錄表!AJ10 -> 0 | K11: =ROUND(I11*J11,0) -> 0
I12: =IF(H12,G12/H12,0) -> 0 | J12: =設備使用記錄表!AJ11 -> 0 | K12: =ROUND(I12*J12,0) -> 0
A13: 小計 | K13: =ROUND(SUM(K6:K12),0) -> 3185
A15: SIIR計畫－設備使用費(2)---新增設備(112年××月)
K16: 金額單位:元
A17: 財產編號 | B17: 設備名稱 | C17: 對照計畫書所列項目 | D17: 取得日期 | E17: 購入成本 (單套) | F17: 套數 B1 | G17: 投入時 單套帳面價值 （未折減餘額） B2 | I17: 每月攤提使用費 B3=B1*B2*/60 (詳如註3) | J17: 本期投入比率 B4 | K17: 本期使用費 B5=B3*B4
A19: (1)1130004 | B19: 商用咖啡機 | C19: 商用咖啡機 | D19: 112.07.01 | E19: 250000 | F19: 1 | G19: 150000 | I19: =F19*G19/60 -> 2500 | J19: =設備使用記錄表!AJ13 -> 1 | K19: =ROUND(I19*J19,0) -> 2500
A20: (2)1130005 | B20: 磨豆機(大) | C20: 磨豆機 | D20: 112.07.01 | E20: 3000 | F20: 1 | G20: 3000 | I20: =F20*G20/60 -> 50 | J20: =設備使用記錄表!AJ14 -> 1 | K20: =ROUND(I20*J20,0) -> 50
A21: (2)1130006 | B21: 磨豆機(中) | C21: 磨豆機 | D21: 112.07.01 | E21: 3000 | F21: 1 | G21: 3000 | I21: =F21*G21/60 -> 50 | J21: =設備使用記錄表!AJ15 -> 0 | K21: =ROUND(I21*J21,0) -> 0
A22: (2)1130007 | B22: 磨豆機(時間型) | C22: 磨豆機 | D22: 112.07.01 | E22: 9000 | F22: 1 | G22: 3000 | I22: =F22*G22/60 -> 50 | J22: =設備使用記錄表!AJ16 -> 0.15625 | K22: =ROUND(I22*J22,0) -> 8
A23: (2)1130008 | B23: 製冰機 | C23: 製冰機 | D23: 112.07.01 | E23: 48000 | F23: 1 | G23: 48000 | I23: =F23*G23/60 -> 800 | J23: =設備使用記錄表!AJ17 -> 1 | K23: =ROUND(I23*J23,0) -> 800
A24: (2)1130009 | B24: 內崁式冰箱 | C24: 內崁式冰箱 | D24: 112.07.01
A25: (2)1130010 | B25: 筆記型電腦(詩) | C25: 筆記型電腦 | D25: 112.07.01
A26: (2)1130011 | B26: 筆記型電腦(諺) | C26: 筆記型電腦
I27: =F27*G27/60 -> 0 | J27: =設備使用記錄表!AJ18 -> 0 | K27: =ROUND(I27*J27,0) -> 0
A28: 小計 | K28: =ROUND(SUM(K18:K27),0) -> 2550
A29: 合計 | K29: =K28+K13 -> 7950
A31: 註1： 「已有設備」及「新增設備」之名稱應與計畫書所列相符並依上表分開填列。
A32: 註2：「本期投入比率」應依據設備使用記錄表實際投入比率一致。
A33: 註3：帳務查核時應備妥下列文件備查:1.新增設備-請購單、採購單、驗收單、統一發票或收據、進口報關結匯單據與INVOICE。
A34: 2.已有設備-財產目錄。3.研發設備使用記錄表。4.若為分攤，應附分攤表及原始憑證影本。
B36: 計畫主持人: | E36: 主辦會計: | J36: 填表人：

Sheet 設備使用記錄表
A1: =計畫經費彙總表!A1 -> 五常物業規劃顧問股份(閉鎖型)有限公司
A2: SIIR計畫設備使用記錄表(113年07月)
B3: 設備名稱 | C3: 1 | D3: 2 | E3: 3 | F3: 4 | G3: 5 | H3: 6 | I3: 7 | J3: 8 | K3: 9 | L3: 10 | M3: 11 | N3: 12 | O3: 13 | P3: 14 | Q3: 15 | R3: 16 | S3: 17 | T3: 18 | U3: 19 | V3: 20 | W3: 21 | X3: 22 | Y3: 23 | Z3: 24 | AA3: 25 | AB3: 26 | AC3: 27 | AD3: 28 | AE3: 29 | AF3: 30 | AG3: 31 | AH3: 合計 | AI3: 正常使用時數 | AJ3: 投入 比率
A5: 已有設備
B6: =IF(設備使用費!C7<>"",設備使用費!C7,"") -> 筆記型電腦 | E6: 8 | F6: 8 | G6: 8 | H6: 8 | I6: 8 | L6: 8 | M6: 8 | N6: 8 | O6: 8 | P6: 4 | S6: 8 | T6: 8 | U6: 8 | V6: 4 | W6: 8 | AH6: =SUM(C6:AG6) -> 112 | AI6: 160 | AJ6: =AH6/AI6 -> 0.7
B7: =IF(設備使用費!C8<>"",設備使用費!C8,"") -> 桌上型電腦 | E7: 8 | F7: 8 | G7: 8 | H7: 8 | I7: 8 | L7: 8 | M7: 8 | N7: 8 | O7: 8 | P7: 8 | S7: 8 | T7: 8 | U7: 8 | V7: 8 | W7: 8 | Z7: 8 | AA7: 8 | AB7: 8 | AC7: 8 | AD7: 8 | AH7: =SUM(C7:AG7) -> 160 | AI7: 160 | AJ7: =AH7/AI7 -> 1
B8: =IF(設備使用費!C9<>"",設備使用費!C9,"") -> 電冰箱 | E8: 8 | F8: 8 | G8: 8 | H8: 8 | I8: 8 | L8: 8 | M8: 8 | N8: 8 | O8: 8 | P8: 8 | S8: 8 | T8: 8 | U8: 8 | V8: 8 | W8: 8 | Z8: 8 | AA8: 8 | AB8: 8 | AC8: 8 | AD8: 8 | AH8: =SUM(C8:AG8) -> 160 | AI8: 160 | AJ8: =AH8/AI8 -> 1
B9: =IF(設備使用費!C10<>"",設備使用費!C10,"") | AH9: =SUM(C9:AG9) -> 0 | AI9: 160 | AJ9: =AH9/AI9 -> 0
B10: =IF(設備使用費!C11<>"",設備使用費!C11,"") | AH10: =SUM(C10:AG10) -> 0 | AI10: 160 | AJ10: =AH10/AI10 -> 0
B11: =IF(設備使用費!C12<>"",設備使用費!C12,"") | AH11: =SUM(C11:AG11) -> 0 | AI11: 160 | AJ11: =AH11/AI11 -> 0
A12: 新增設備
B13: =IF(設備使用費!C19<>"",設備使用費!C19,"") -> 商用咖啡機 | E13: 8 | F13: 8 | G13: 8 | H13: 8 | I13: 8 | L13: 8 | M13: 8 | N13: 8 | O13: 8 | P13: 8 | S13: 8 | T13: 8 | U13: 8 | V13: 8 | W13: 8 | Z13: 8 | AA13: 8 | AB13: 8 | AC13: 8 | AD13: 8 | AH13: =SUM(C13:AG13) -> 160 | AI13: 160 | AJ13: =AH13/AI13 -> 1
B14: =IF(設備使用費!C20<>"",設備使用費!C20,"") -> 磨豆機 | E14: 8 | F14: 8 | G14: 8 | H14: 8 | I14: 8 | L14: 8 | M14: 8 | N14: 8 | O14: 8 | P14: 8 | S14: 8 | T14: 8 | U14: 8 | V14: 8 | W14: 8 | Z14: 8 | AA14: 8 | AB14: 8 | AC14: 8 | AD14: 8 | AH14: =SUM(C14:AG14) -> 160 | AI14: 160 | AJ14: =AH14/AI14 -> 1
B15: =IF(設備使用費!C21<>"",設備使用費!C21,"") -> 磨豆機 | E15: 3 | G15: 2 | H15: 1 | I15: 1 | L15: 1 | M15: 1 | N15: 1 | O15: 1 | P15: 1 | S15: 2 | T15: 1 | AB15: {=+AB15:AE15} -> 0 | AH15: =SUM(C15:AG15) -> 0 | AI15: 160 | AJ15: =AH15/AI15 -> 0
B16: =IF(設備使用費!C22<>"",設備使用費!C22,"") -> 磨豆機 | E16: 1 | F16: 1 | G16: 1 | H16: 1 | I16: 1 | L16: 1 | M16: 1 | N16: 1 | O16: 1 | P16: 1 | S16: 1 | T16: 1 | U16: 1 | Z16: 1 | AA16: 1 | AB16: 1 | AC16: 1 | AD16: 8 | AH16: =SUM(C16:AG16) -> 25 | AI16: 160 | AJ16: =AH16/AI16 -> 0.15625
B17: =IF(設備使用費!C23<>"",設備使用費!C23,"") -> 製冰機 | E17: 8 | F17: 8 | G17: 8 | H17: 8 | I17: 8 | L17: 8 | M17: 8 | N17: 8 | O17: 8 | P17: 8 | S17: 8 | T17: 8 | U17: 8 | V17: 8 | W17: 8 | Z17: 8 | AA17: 8 | AB17: 8 | AC17: 8 | AD17: 8 | AH17: =SUM(C17:AG17) -> 160 | AI17: 160 | AJ17: =AH17/AI17 -> 1
B18: =IF(設備使用費!C27<>"",設備使用費!C27,"") | AH18: =SUM(C18:AG18) -> 0 | AI18: 160 | AJ18: =AH18/AI18 -> 0
V19: {=+V19:KA20} -> 0
A20: 註1.當月正常使用總時數與人員上班時數相同；若設備為24小時開機者，則以24小時*當月日數，計算當月正常使用總時數。
A21: 註2.每月投入比率最高為1.00。
A22: 註3.攤提設備名稱請參照計畫書所編列設備。
C24: 計畫主持人: | O24: 主辦會計: | X24: 填表人：

Sheet 設備維護費
A1: =計畫經費彙總表!A1 -> 五常物業規劃顧問股份(閉鎖型)有限公司
A2: SIIR計畫設備維護費---已有設備(112年××月)
M3: 金額單位:元
A4: 財產編號 | C4: 設備名稱 | D4: 對照計畫書所列項目 | E4: 購入成本 | F4: 傳票日期 | G4: 傳票號碼 | H4: 發票日期 | I4: 發票編號 | J4: 品名 | K4: 數量 | L4: 單位 | M4: 金額
A16: 小 計(A) | M16: =ROUND(SUM(M5:M15),0) -> 0
A18: 註1：所列報之維護設備應與計畫書所列相符，並應出具維修廠商憑證，且所列維護費之金額應與原始憑證、費用分攤表相符。
A19: 註2：營業稅不得報支。新增設備保固期間內不得列報維護費。
A20: 註3：若屬廠商自行維修之設備，維護費不得超出原購入成本之5%。
A21: 註4：帳務查核時應備妥下列文件備查:1.請購單、驗收單、維護合約、發票或收據等。2.屬自行維修性質者應提供「設備維修時間記錄表」
A22: 及相關自行維修成本計算表。3.若為分攤，應附分攤表及原始憑證影本。4.涉及外幣支付時應附當時之外幣 匯率表。
B24: 計畫主持人: | F24: 主辦會計: | K24: 填表人：

Sheet 技術購買費
A1: =計畫經費彙總表!A1 -> 五常物業規劃顧問股份(閉鎖型)有限公司
A2: SIIR計畫－技術或智慧財產權購買費(113年07月)
A4: 1.技轉(委託)項目:咖啡製作技術、咖啡及飲品共15品項製作配方、製作工序、原料商 | B4: 咖啡製作技術、咖啡及飲品共15品項製作配方、製作工序、原料商 | E4: 2.技轉(委託)對象： | F4: 本司派出之技術承接專員
A5: 3.合約期間:00年00月00日~00年00月00日 | E5: 4.合約總額：新台幣肆拾萬元整
A6: 5.付款方式：依合約內容 | F6: 金額單位:元
A7: 付款期數 | B7: 傳票日期 | C7: 傳票號碼 | D7: 發票日期 | E7: 發票編號 | F7: 金額
A8: 第 1 期 | F8: 150000
A9: 第 2 期 | F9: 150000
A15: 合 計 | F15: =ROUND(SUM(F8:F14),0) -> 300000
A17: 註1：營業稅不得報支。
A18: 註2：技術購買之對象應與計畫書所列相符，金額應與原始憑證（如：統一發票或收據）相符。
A19: 註3：帳務查核時應備妥下列文件備查:1.技術購買契約書。(2)統一發票（或收據）、或國外之INVOICE(或RECEIPT)及匯兌水單。
A21: 計畫主持人: | D21: 主辦會計: | F21: 填表人：

Sheet 委託研究費
A1: =計畫經費彙總表!A1 -> 五常物業規劃顧問股份(閉鎖型)有限公司
A2: SIIR計畫－委託研究費(112年××月)
A4: 1.技轉(委託)項目: | E4: 2.技轉(委託)對象：
A5: 3.合約期間:113年07月01日~114年07月01日 | E5: 4.合約總額：
A6: 5.付款方式： | F6: 金額單位:元
A7: 付款期數 | B7: 傳票日期 | C7: 傳票號碼 | D7: 發票日期 | E7: 發票編號 | F7: 金額
A8: 第 1 期 | E8: AV23182456 | F8: 200000
A9: 第 2 期 | E9: EW86973745 | F9: 150000
A15: 合 計 | F15: =ROUND(SUM(F8:F14),0) -> 350000
A17: 註1：營業稅不得報支。
A18: 註2：委託研究之對象應與計畫書所列相符，金額應與原始憑證（如：統一發票或收據）相符。
A19: 註3：帳務查核時應備妥下列文件備查:1.委託研究契約書。(2)統一發票（或收據）、或國外之INVOICE(或RECEIPT)及匯兌水單。
A21: 計畫主持人: | C21: 主辦會計: | E21: 填表人：

Sheet 委託勞務費
A1: =計畫經費彙總表!A1 -> 五常物業規劃顧問股份(閉鎖型)有限公司
A2: SIIR計畫－委託勞務費(112年××月)
A4: 1.技轉(委託)項目: | E4: 2.技轉(委託)對象：
A5: 3.合約期間:00年00月00日~00年00月00日 | E5: 4.合約總額：
A6: 5.付款方式： | F6: 金額單位:元
A7: 付款期數 | B7: 傳票日期 | C7: 傳票號碼 | D7: 發票日期 | E7: 發票編號 | F7: 金額
A8: 第 1 期 | E8: AV23182456 | F8: 300000
A9: 第 2 期 | E9: EW86973745 | F9: 100000
A15: 合 計 | F15: =ROUND(SUM(F8:F14),0) -> 400000
A17: 註1：營業稅不得報支。
A18: 註2：委託勞務之對象應與計畫書所列相符，金額應與原始憑證（如：統一發票或收據）相符。
A19: 註3：帳務查核時應備妥下列文件備查:1.委託勞務契約書。(2)統一發票（或收據）、或國外之INVOICE(或RECEIPT)及匯兌水單。
A21: 計畫主持人: | D21: 主辦會計: | F21: 填表人：

Sheet 國內差旅費
A1: =計畫經費彙總表!A1 -> 五常物業規劃顧問股份(閉鎖型)有限公司
A2: SIIR計畫－國內差旅費(112年××月)
N3: 金額單元:元
A4: 姓名 | B4: 職稱 | C4: 出差期間 | D4: 天數 | E4: 地點 | F4: 事 由 | G4: 傳票日期 | H4: 傳票號碼 | I4: 機票 | J4: 車資 | K4: 住宿費 | L4: 膳雜費 | M4: 其他 | N4: 合計
B6: 經理 | C6: 3月14-15日 | D6: 2 | E6: 塑膠中心 | F6: 討論勞務規格 | J6: 300 | K6: 1000 | L6: 550 | N6: =ROUND(SUM(I6:M6),0) -> 1850
B7: 工程師 | N7: =ROUND(SUM(I7:M7),0) -> 0
N8: =ROUND(SUM(I8:M8),0) -> 0
N9: =ROUND(SUM(I9:M9),0) -> 0
N10: =ROUND(SUM(I10:M10),0) -> 0
N11: =ROUND(SUM(I11:M11),0) -> 0
N12: =ROUND(SUM(I12:M12),0) -> 0
N13: =ROUND(SUM(I13:M13),0) -> 0
A14: 合 計 | N14: =ROUND(SUM(N5:N13),0) -> 1850
A16: 註1：出差人員僅限本計畫計畫人員，且出差事由應與本專案計畫有關。
A17: 註2：差旅費之膳雜費計算應不超過營利事業所得稅查核準則規定。
A18: 註3：帳務查核時應備妥下列文件備查:(1)搭乘飛機，應檢附機票票根或登機證存根及國際線航空機票購票證明單或旅行業代收轉付收據；
A19: 其餘交通費，應檢附原始單據或旅行業代收轉付 收據。(2)乘坐輪船，應提供船票或輪船公司出具之證明。
A20: (3)火車、汽車之車資，以經手人（即出差人）之證明為憑。但包租計程車應取具車行證明及經手人或出差人證明。(4)住宿費收據或發票。
A21: (5)出差報銷單及公司差旅費報銷規定。(6)涉及外幣支付時應附當時之外幣匯率表。
B22: 計畫主持人: | F22: 主辦會計: | K22: 填表人：

Sheet 國外差旅費
A1: =計畫經費彙總表!A1 -> 五常物業規劃顧問股份(閉鎖型)有限公司
A2: SIIR計畫－國外差旅費(112年××月)
N3: 金額單元:元
A4: 姓名 | B4: 職稱 | C4: 出差期間 | D4: 天數 | E4: 地點 | F4: 事 由 | G4: 傳票日期 | H4: 傳票號碼 | I4: 機票 | J4: 車資 | K4: 住宿費 | L4: 膳雜費 | M4: 其他 | N4: 合計
A6: 1.××× | B6: 經理 | C6: 3月17-18日 | D6: 2 | E6: XX | F6: 討論勞務規格 | I6: 1000 | K6: 450 | L6: 550 | N6: =ROUND(SUM(I6:M6),0) -> 2000
A7: 2.××× | B7: 工程師 | N7: =ROUND(SUM(I7:M7),0) -> 0
N8: =ROUND(SUM(I8:M8),0) -> 0
N9: =ROUND(SUM(I9:M9),0) -> 0
N10: =ROUND(SUM(I10:M10),0) -> 0
N11: =ROUND(SUM(I11:M11),0) -> 0
N12: =ROUND(SUM(I12:M12),0) -> 0
N13: =ROUND(SUM(I13:M13),0) -> 0
A14: 合 計 | N14: =ROUND(SUM(N5:N13),0) -> 2000
A16: 註1：出差人員僅限本計畫計畫人員，且出差事由應與本專案計畫有關。
A17: 註2：差旅費之膳雜費計算應不超過營利事業所得稅查核準則規定。
A18: 註3：帳務查核時應備妥下列文件備查:(1)搭乘飛機，應檢附機票票根或登機證存根及國際線航空機票購票證明單或旅行業代收轉付收據；
A19: 其餘交通費，應檢附原始單據或旅行業代收轉付 收據。(2)乘坐輪船，應提供船票或輪船公司出具之證明。
A20: (3)火車、汽車之車資，以經手人（即出差人）之證明為憑。但包租計程車應取具車行證明及經手人或出差人證明。(4)住宿費收據或發票。
A21: (5)出差報銷單及公司差旅費報銷規定。(6)涉及外幣支付時應附當時之外幣匯率表。
B22: 計畫主持人: | F22: 主辦會計: | K22: 填表人：

Sheet 市場驗證費
A1: =計畫經費彙總表!A1 -> 五常物業規劃顧問股份(閉鎖型)有限公司
A2: SIIR計畫－市場驗證費(112年××月)
J3: 金額單位:元
A4: 傳票日期 | B4: 傳票號碼 | C4: 發票日期 | D4: 發票編號 | E4: 供應商 | F4: 發票內容 (註2) | G4: 對照計畫書所列項目 (註1) | H4: 數量 | I4: 單價 | J4: 金額 (不含營業稅)
A6: 112.4.22 | D6: AB12345678 | E6: ×× | H6: 1 | J6: 1200
A7: 112.4.25 | D7: AB13145676 | E7: ×× | H7: 3 | J7: 6000
A18: 合 計 | J18: =ROUND(SUM(J5:J17),0) -> 7200
A20: 註1：「對照計畫書所列項目」名稱需與計畫書所列之項目名稱一致。
A21: 註2：「發票內容」請依發票填寫所列項目。
A22: 註3：營業稅不得報支。
A23: 註4：帳務查核時應備妥下列文件備查:1.應提供統一發票、收據或進口結匯單據與invoice。2.涉及外幣支付時應附當時之外幣匯率表。3、廣告樣張（樣張上應印有營利事業名稱
A24: 、品牌名或與計畫有相關之資訊)。
A25: 註5：贈送樣品或商品饋贈之項目上限不得逾本科目10%，單份不得逾新台幣500元。
A26: 註6：贊助公益或體育活動具有廣告性質之各項費用應取得統一發票或合法憑證，並檢附載有活動名稱及營利事業名稱之相關廣告品。
A27: 註7：活動臨時聘用人力費用須提供如人事費科目之查核資料。
A28: 註8：活動臨時聘用人力費用，時薪不得低於政府公告最低時薪標準，且不得超過本經費科目10%。
A30: 計畫主持人: | F30: 主辦會計: | I30: 填表人：

Sheet 工作表2

Sheet 工作表1
