Workbook

Sheet 11月現金日記帳
A1: 聊閣咖啡仁義店日記帳 | L1: 現金流量表
A2: 日期 | B2: 營業收入 | C2: 現金收入 | D2: linepay | E2: 街口支付 | F2: 烘爸銷售額 | G2: 點點付 | H2: 雜項費用 | I2: 營業費用總額 | J2: 帳差額 | M2: 借方 | N2: 貸方 | O2: 餘額 | P2: 項目盈損
A3: 45597 | B3: 1630 | H3: ='11月費用明細憑證'!E3 -> 0 | I3: =H3+(F3*0.7) -> 0 | J3: =(B3-C3-D3-E3-G3) -> 1630 | L3: 營業收入 | M3: =SUM(C3:C32) -> 0 | N3: =N4 -> 0 | O3: =M3-N3 -> 0 | P3: =N3 -> 0
A4: 45598 | B4: 2638 | H4: ='11月費用明細憑證'!E4 -> 0 | I4: =H4+(F4*0.7) -> 0 | J4: =(B4-C4-D4-E4-G4) -> 2638 | L4: 現金收支總額 | M4: =SUM(C3:C33)+M9 -> 0 | N4: =M7+O7 -> 0 | O4: =M4-N4 -> 0
A5: 45599 | B5: 1066 | H5: ='11月費用明細憑證'!E5 -> 0 | I5: =H5+(F5*0.7) -> 0 | J5: =(B5-C5-D5-E5-G5) -> 1066 | L5: 銀行帳戶 | O5: =M5-N5 -> 0 | P5: =M5-N5 -> 0
A6: 45600 | B6: 1761 | H6: ='11月費用明細憑證'!E6 -> 0 | I6: =H6+(F6*0.7) -> 0 | J6: =(B6-C6-D6-E6-G6) -> 1761 | L6: 現金帳餘額 | M6: =M9+M10-M11+O7 -> 0 | O6: =M6-N6 -> 0
A7: 45601 | B7: 1032 | H7: ='11月費用明細憑證'!E7 -> 0 | I7: =H7+(F7*0.7) -> 0 | J7: =(B7-C7-D7-E7-G7) -> 1032 | L7: 各項費用 | M7: =C35 -> 0 | N7: 代銷成本 | O7: =F35 -> 0
A8: 45602 | B8: 1736 | H8: ='11月費用明細憑證'!E8 -> 0 | I8: =H8+(F8*0.7) -> 0 | J8: =(B8-C8-D8-E8-G8) -> 1736
A9: 45603 | B9: 1864 | H9: ='11月費用明細憑證'!E9 -> 0 | I9: =H9+(F9*0.7) -> 0 | J9: =(B9-C9-D9-E9-G9) -> 1864 | L9: 公司戶進出
A10: 45604 | B10: 495 | H10: ='11月費用明細憑證'!E10 -> 0 | I10: =H10+(F10*0.7) -> 0 | J10: =(B10-C10-D10-E10-G10) -> 495 | L10: 稅前毛利 | M10: =O3 -> 0
A11: 45605 | B11: 2143 | H11: ='11月費用明細憑證'!E11 -> 0 | I11: =H11+(F11*0.7) -> 0 | J11: =(B11-C11-D11-E11-F11) -> 2143 | L11: 人事費
A12: 45606 | B12: 2956 | H12: ='11月費用明細憑證'!E12 -> 0 | I12: =H12+(F12*0.7) -> 0 | J12: =(B12-C12-D12-E12-G11) -> 2956 | L12: 當月損益 | M12: =M10-M11 -> 0
A13: 45607 | B13: 1528 | H13: ='11月費用明細憑證'!E13 -> 0 | I13: =H13+(F13*0.7) -> 0 | J13: =(B13-C13-D13-E13-G13) -> 1528
A14: 45608 | H14: ='11月費用明細憑證'!E14 -> 0 | I14: =H14+(F14*0.7) -> 0 | J14: =(B14-C14-D14-E14-G14) -> 0
A15: 45609 | H15: ='11月費用明細憑證'!E15 -> 0 | I15: =H15+(F15*0.7) -> 0 | J15: =(B15-C15-D15-E15-G15) -> 0
A16: 45610 | H16: ='11月費用明細憑證'!E16 -> 0 | I16: =H16+(F16*0.7) -> 0 | J16: =(B16-C16-D16-E16-G16) -> 0 | L16: 紅字→多錢
A17: 45611 | H17: ='11月費用明細憑證'!E17 -> 0 | I17: =H17+(F17*0.7) -> 0 | J17: =(B17-C17-D17-E17-G17) -> 0 | L17: 黑字→少錢
A18: 45612 | H18: ='11月費用明細憑證'!E18 -> 0 | I18: =H18+(F18*0.7) -> 0 | J18: =(B18-C18-D18-E18-G18) -> 0
A19: 45613 | H19: ='11月費用明細憑證'!E19 -> 0 | I19: =H19+(F19*0.7) -> 0 | J19: =(B19-C19-D19-E19-G19) -> 0
A20: 45614 | H20: ='11月費用明細憑證'!E20 -> 0 | I20: =H20+(F20*0.7) -> 0 | J20: =(B20-C20-D20-E20-G20) -> 0
A21: 45615 | H21: ='11月費用明細憑證'!E21 -> 0 | I21: =H21+(F21*0.7) -> 0 | J21: =(B21-C21-D21-E21-G21) -> 0
A22: 45616 | H22: ='11月費用明細憑證'!E22 -> 0 | I22: =H22+(F22*0.7) -> 0 | J22: =(B22-C22-D22-E22-G22) -> 0
A23: 45617 | H23: ='11月費用明細憑證'!E23 -> 0 | I23: =H23+(F23*0.7) -> 0 | J23: =(B23-C23-D23-E23-G23) -> 0
A24: 45618 | H24: ='11月費用明細憑證'!E24 -> 0 | I24: =H24+(F24*0.7) -> 0 | J24: =(B24-C24-D24-E24-G24) -> 0
A25: 45619 | H25: ='11月費用明細憑證'!E25 -> 0 | I25: =H25+(F25*0.7) -> 0 | J25: =(B25-C25-D25-E25-G25) -> 0
A26: 45620 | H26: ='11月費用明細憑證'!E26 -> 0 | I26: =H26+(F26*0.7) -> 0 | J26: =(B26-C26-D26-E26-G26) -> 0
A27: 45621 | H27: ='11月費用明細憑證'!E27 -> 0 | I27: =H27+(F27*0.7) -> 0 | J27: =(B27-C27-D27-E27-G27) -> 0
A28: 45622 | H28: ='11月費用明細憑證'!E28 -> 0 | I28: =H28+(F28*0.7) -> 0 | J28: =(B28-C28-D28-E28-G28) -> 0
A29: 45623 | H29: ='11月費用明細憑證'!E29 -> 0 | I29: =H29+(F29*0.7) -> 0 | J29: =(B29-C29-D29-E29-G29) -> 0
... A33: 45627 | H33: ='11月費用明細憑證'!E33 -> 0 | I33: =H33+(F33*0.7) -> 0 | J33: =(B33-C33-D33-E33-G33) -> 0
A34: 項目 | B34: 月營業額 | C34: 費用總額 | D34: 毛利 | F34: 烘爸帳款 | G34: 帳面餘絀 | H34: 每股可分淨額
A35: 小計 | B35: =SUM(B3:B33) -> 18849 | C35: =SUM(H3:H33) -> 0 | D35: =B35-C35 -> 18849 | F35: =SUM(F3:F33)*0.7 -> 0 | G35: =SUM(J3:J33) -> 18849 | H35: =O8/3 -> 0

Sheet 10月現金日記帳
A1: 聊閣咖啡仁義店日記帳 | L1: 現金流量表
A2: 日期 | B2: 營業收入 | C2: 現金收入 | D2: linepay | E2: 街口支付 | F2: 烘爸銷售額 | G2: 點點付 | H2: 雜項費用 | I2: 營業費用總額 | J2: 帳差額 | M2: 借方 | N2: 貸方 | O2: 餘額 | P2: 項目盈損
A3: 45566 | B3: 1997 | C3: 2176 | F3: =260+50 -> 310 | H3: ='10月費用明細憑證'!E3 -> 0 | I3: =H3+(F3*0.7) -> 217 | J3: =(B3-C3-D3-E3-G3) -> -179 | L3: 營業收入 | M3: =SUM(C3:C32) -> 50741 | N3: =N4 -> 76530.5 | O3: =M3-N3 -> -25789.5 | P3: =N3 -> 76530.5
A4: 45567 | B4: 2699 | C4: 2275 | F4: =385 -> 385 | H4: ='10月費用明細憑證'!E4 -> 0 | I4: =H4+(F4*0.7) -> 269.5 | J4: =(B4-C4-D4-E4-G4) -> 424 | L4: 現金收支總額 | M4: =SUM(C3:C33)+M9 -> 123707 | N4: =M7+O7 -> 76530.5 | O4: =M4-N4 -> 47176.5
A5: 45568 | B5: 920 | C5: 1000 | F5: 0 | H5: ='10月費用明細憑證'!E5 -> 290 | I5: =H5+(F5*0.7) -> 290 | J5: =(B5-C5-D5-E5-G5) -> -80 | L5: 銀行帳戶 | M5: =76+36000 -> 36076 | N5: =36000 -> 36000 | O5: =M5-N5 -> 76 | P5: =M5-N5 -> 76
A6: 45569 | B6: =1345+360 -> 1705 | C6: =1730+360 -> 2090 | F6: =60+80+100 -> 240 | H6: ='10月費用明細憑證'!E6 -> 37042 | I6: =H6+(F6*0.7) -> 37210 | J6: =(B6-C6-D6-E6-G6) -> -385 | L6: 現金帳餘額 | M6: =M9+M10-M11+O7 -> 51226 | O6: =M6-N6 -> 51226
A7: 45570 | B7: =1214-360 -> 854 | C7: 930 | F7: 110 | H7: ='10月費用明細憑證'!E7 -> 2550 | I7: =H7+(F7*0.7) -> 2627 | J7: =(B7-C7-D7-E7-G7) -> -76 | L7: 各項費用 | M7: =C35 -> 72481 | N7: 代銷成本 | O7: =F35 -> 4049.5
A8: 45571 | B8: 2118 | C8: 2070 | F8: 0 | H8: ='10月費用明細憑證'!E8 -> 3552 | I8: =H8+(F8*0.7) -> 3552 | J8: =(B8-C8-D8-E8-G8) -> 48
A9: 45572 | B9: 2275 | C9: 2280 | F9: =60+580 -> 640 | H9: ='10月費用明細憑證'!E9 -> 0 | I9: =H9+(F9*0.7) -> 448 | J9: =(B9-C9-D9-E9-G9) -> -5 | L9: 公司戶進出 | M9: =25927+30000+17039 -> 72966
A10: 45573 | B10: 1855 | C10: 1870 | F10: 110 | H10: ='10月費用明細憑證'!E10 -> 1110 | I10: =H10+(F10*0.7) -> 1187 | J10: =(B10-C10-D10-E10-G10) -> -15 | L10: 稅前毛利 | M10: =O3 -> -25789.5
A11: 45574 | B11: 2061 | C11: 2100 | F11: 0 | H11: ='10月費用明細憑證'!E11 -> 500 | I11: =H11+(F11*0.7) -> 500 | J11: =(B11-C11-D11-E11-F11) -> -39 | L11: 人事費
A12: 45575 | B12: 2356 | C12: 2110 | F12: 315 | H12: ='10月費用明細憑證'!E12 -> 0 | I12: =H12+(F12*0.7) -> 220.5 | J12: =(B12-C12-D12-E12-G11) -> 246 | L12: 當月損益 | M12: =M10-M11 -> -25789.5
A13: 45576 | B13: 1259 | C13: 1715 | F13: 220 | H13: ='10月費用明細憑證'!E13 -> 0 | I13: =H13+(F13*0.7) -> 154 | J13: =(B13-C13-D13-E13-G13) -> -456
A14: 45577 | B14: 1786 | C14: 2140 | F14: =40 -> 40 | H14: ='10月費用明細憑證'!E14 -> 0 | I14: =H14+(F14*0.7) -> 28 | J14: =(B14-C14-D14-E14-G14) -> -354
A15: 45578 | B15: 4502 | C15: 4310 | F15: 60 | G15: 130 | H15: ='10月費用明細憑證'!E15 -> 0 | I15: =H15+(F15*0.7) -> 42 | J15: =(B15-C15-D15-E15-G15) -> 62
A16: 45579 | B16: 1162 | C16: 1230 | F16: 0 | H16: ='10月費用明細憑證'!E16 -> 235 | I16: =H16+(F16*0.7) -> 235 | J16: =(B16-C16-D16-E16-G16) -> -68 | L16: 紅字→多錢
A17: 45580 | B17: 1640 | C17: 1710 | F17: 140 | H17: ='10月費用明細憑證'!E17 -> 3535 | I17: =H17+(F17*0.7) -> 3633 | J17: =(B17-C17-D17-E17-G17) -> -70 | L17: 黑字→少錢
A18: 45581 | B18: 1430 | C18: 1355 | F18: =360+55 -> 415 | H18: ='10月費用明細憑證'!E18 -> 6070 | I18: =H18+(F18*0.7) -> 6360.5 | J18: =(B18-C18-D18-E18-G18) -> 75
A19: 45582 | B19: 1260 | C19: 600 | F19: =180+220 -> 400 | H19: ='10月費用明細憑證'!E19 -> 0 | I19: =H19+(F19*0.7) -> 280 | J19: =(B19-C19-D19-E19-G19) -> 660
A20: 45583 | B20: 1936 | C20: 2131 | F20: =120+190+50 -> 360 | H20: ='10月費用明細憑證'!E20 -> 0 | I20: =H20+(F20*0.7) -> 252 | J20: =(B20-C20-D20-E20-G20) -> -195
A21: 45584 | B21: 2253 | C21: 2201 | F21: =550+60 -> 610 | H21: ='10月費用明細憑證'!E21 -> 0 | I21: =H21+(F21*0.7) -> 427 | J21: =(B21-C21-D21-E21-G21) -> 52
A22: 45585 | B22: 964 | C22: 400 | F22: 0 | H22: ='10月費用明細憑證'!E22 -> 300 | I22: =H22+(F22*0.7) -> 300 | J22: =(B22-C22-D22-E22-G22) -> 564
A23: 45586 | B23: 1690 | C23: 1700 | F23: =120+250 -> 370 | H23: ='10月費用明細憑證'!E23 -> 1570 | I23: =H23+(F23*0.7) -> 1829 | J23: =(B23-C23-D23-E23-G23) -> -10
A24: 45587 | B24: 1829 | C24: 1753 | F24: =120+220 -> 340 | G24: 80 | H24: ='10月費用明細憑證'!E24 -> 0 | I24: =H24+(F24*0.7) -> 238 | J24: =(B24-C24-D24-E24-G24) -> -4
A25: 45588 | B25: 2233 | C25: 2133 | F25: =220 -> 220 | H25: ='10月費用明細憑證'!E25 -> 0 | I25: =H25+(F25*0.7) -> 154 | J25: =(B25-C25-D25-E25-G25) -> 100
A26: 45589 | B26: 341 | C26: 370 | F26: 0 | H26: ='10月費用明細憑證'!E26 -> 0 | I26: =H26+(F26*0.7) -> 0 | J26: =(B26-C26-D26-E26-G26) -> -29
A27: 45590 | B27: 1441 | C27: 1100 | F27: 0 | H27: ='10月費用明細憑證'!E27 -> 11700 | I27: =H27+(F27*0.7) -> 11700 | J27: =(B27-C27-D27-E27-G27) -> 341
A28: 45591 | B28: 2481 | C28: 2500 | F28: =230+100+60 -> 390 | H28: ='10月費用明細憑證'!E28 -> 0 | I28: =H28+(F28*0.7) -> 273 | J28: =(B28-C28-D28-E28-G28) -> -19
A29: 45592 | B29: 2362 | C29: 2400 | F29: 0 | H29: ='10月費用明細憑證'!E29 -> 712 | I29: =H29+(F29*0.7) -> 712 | J29: =(B29-C29-D29-E29-G29) -> -38
A30: 45593 | B30: 955 | C30: 1000 | F30: 0 | H30: ='10月費用明細憑證'!E30 -> 0 | I30: =H30+(F30*0.7) -> 0 | J30: =(B30-C30-D30-E30-G30) -> -45
A31: 45594 | B31: 2719 | C31: 400 | F31: 0 | H31: ='10月費用明細憑證'!E31 -> 2400 | I31: =H31+(F31*0.7) -> 2400 | J31: =(B31-C31-D31-E31-G31) -> 2319
A32: 45595 | B32: 692 | C32: 692 | F32: 110 | H32: ='10月費用明細憑證'!E32 -> 915 | I32: =H32+(F32*0.7) -> 992 | J32: =(B32-C32-D32-E32-G32) -> 0
A33: 45596 | B33: 0 | C33: 0 | F33: 0 | H33: ='10月費用明細憑證'!E34 -> 0 | I33: =H33+(F33*0.7) -> 0 | J33: =(B33-C33-D33-E33-G33) -> 0
A34: 項目 | B34: 月營業額 | C34: 費用總額 | D34: 毛利 | F34: 烘爸帳款 | G34: 帳面餘絀 | H34: 每股可分淨額
A35: 小計 | B35: =SUM(B3:B33) -> 53775 | C35: =SUM(H3:H33) -> 72481 | D35: =B35-C35 -> -18706 | F35: =SUM(F3:F33)*0.7 -> 4049.5 | G35: =SUM(J3:J33) -> 2824 | H35: =O8/3 -> 0

Sheet 11月費用明細憑證
A1: 聊閣咖啡仁義店支出費用明細
A2: 費用明細表 | B2: 食材成本 | C2: 固定成本 | D2: 變動成本 | E2: 費用小計 | F2: 項目明細 | G2: 支付憑證
A3: 45566 | E3: =SUM(B3:D3) -> 0 | G3: 10月憑證
A4: 45567 | E4: =SUM(B4:D4) -> 0
A5: 45568 | E5: =SUM(B5:D5) -> 0
A6: 45569 | E6: =SUM(B6:D6) -> 0
A7: 45570 | E7: =SUM(B7:D7) -> 0
A8: 45571 | E8: =SUM(B8:D8) -> 0
A9: 45572 | E9: =SUM(B9:D9) -> 0
A10: 45573 | E10: =SUM(B10:D10) -> 0
A11: 45574 | E11: =SUM(B11:D11) -> 0
A12: 45575 | E12: =SUM(B12:D12) -> 0
A13: 45576 | E13: =SUM(B13:D13) -> 0
A14: 45577 | E14: =SUM(B14:D14) -> 0
A15: 45578 | E15: =SUM(B15:D15) -> 0
... A32: 45595 | E32: =SUM(B32:D32) -> 0
A33: 45596
A34: 未結應付賬款
A35: 小計 | E35: =SUM(E3:E32) -> 0

Sheet 10月費用明細憑證
A1: 聊閣咖啡仁義店支出費用明細
A2: 費用明細表 | B2: 食材成本 | C2: 固定成本 | D2: 變動成本 | E2: 費用小計 | F2: 項目明細 | G2: 支付憑證
A3: 45566 | E3: =SUM(B3:D3) -> 0 | G3: 10月憑證
A4: 45567 | E4: =SUM(B4:D4) -> 0
A5: 45568 | D5: 290 | E5: =SUM(B5:D5) -> 290 | F5: 咖啡器具(粉碗) 290
A6: 45569 | B6: 750 | C6: 36000 | D6: =30+262 -> 292 | E6: =SUM(B6:D6) -> 37042 | F6: 鮮奶 750 匯費 30 房租 36000 馬克杯 262
A7: 45570 | D7: 2550 | E7: =SUM(B7:D7) -> 2550 | F7: 錯帳調整 2550
A8: 45571 | B8: =2800+90 -> 2890 | D8: =238+424 -> 662 | E8: =SUM(B8:D8) -> 3552 | F8: 玻璃杯 238 咖啡器具 424 食材 2800 厚片 90
A9: 45572 | E9: =SUM(B9:D9) -> 0
A10: 45573 | B10: =290+820 -> 1110 | E10: =SUM(B10:D10) -> 1110 | F10: 多多 290 果醬 820
A11: 45574 | B11: 500 | E11: =SUM(B11:D11) -> 500 | F11: 鮮奶 500 匯費 15
A12: 45575 | E12: =SUM(B12:D12) -> 0
A13: 45576 | E13: =SUM(B13:D13) -> 0
A14: 45577 | E14: =SUM(B14:D14) -> 0
A15: 45578 | E15: =SUM(B15:D15) -> 0
A16: 45579 | B16: 235 | E16: =SUM(B16:D16) -> 235 | F16: 厚片 235
A17: 45580 | B17: =1700+1070+750 -> 3520 | D17: 15 | E17: =SUM(B17:D17) -> 3535 | F17: 1700 開元 1870 匯費 15
A18: 45581 | D18: 6070 | E18: =SUM(B18:D18) -> 6070 | F18: 保險 6070
A19: 45582 | E19: =SUM(B19:D19) -> 0
A20: 45583 | E20: =SUM(B20:D20) -> 0
A21: 45584 | E21: =SUM(B21:D21) -> 0
A22: 45585 | D22: 300 | E22: =SUM(B22:D22) -> 300
A23: 45586 | B23: 500 | D23: =140+900+30 -> 1070 | E23: =SUM(B23:D23) -> 1570 | F23: 鮮奶 500 飯模 140 易達豐 900 匯費 30
A24: 45587 | E24: =SUM(B24:D24) -> 0
A25: 45588 | E25: =SUM(B25:D25) -> 0
A26: 45589 | E26: =SUM(B26:D26) -> 0
A27: 45590 | D27: 11700 | E27: =SUM(B27:D27) -> 11700 | F27: 商標註冊及專利技術年費 11700
A28: 45591 | E28: =SUM(B28:D28) -> 0
A29: 45592 | D29: =199+513 -> 712 | E29: =SUM(B29:D29) -> 712 | F29: 咖啡器具 199 玻璃杯 513
A30: 45593 | E30: =SUM(B30:D30) -> 0
A31: 45594 | D31: 2400 | E31: =SUM(B31:D31) -> 2400 | F31: 標籤貼紙 2400
A32: 45595 | B32: 900 | D32: 15 | E32: =SUM(B32:D32) -> 915 | F32: 金桔汁 900 匯費 15
A33: 45596 | D33: 1757 | F33: 單位負擔健保 1757
A34: 未結應付賬款
A35: 小計 | E35: =SUM(E3:E32) -> 72481

Sheet 9月現金日記帳
A1: 聊閣咖啡仁義店日記帳 | L1: 現金流量表
A2: 日期 | B2: 營業收入 | C2: 現金收入 | D2: linepay | E2: 街口支付 | F2: 烘爸銷售額 | G2: 點點付 | H2: 雜項費用 | I2: 營業費用總額 | J2: 帳差額 | M2: 金額 | N2: 月變動額度 | O2: 餘額 | P2: 項目盈損
A3: 45536 | H3: ='9月費用明細憑證'!E3 -> 0 | I3: =H3+(F3*0.7) -> 0 | J3: =(B3-C3-D3-E3-G3-I3) -> 0 | L3: 營業收入 | M3: =SUM(C3:C32) -> 51011 | N3: =N4 -> 45084.3 | O3: =M3-N3 -> 5926.7 | P3: =N3 -> 45084.3
A4: 45537 | H4: ='9月費用明細憑證'!E4 -> 0 | I4: =H4+(F4*0.7) -> 0 | J4: =(B4-C4-D4-E4-G4-I4) -> 0 | L4: 現金收支總額 | M4: =SUM(C3:C33)+M9 -> 71011 | N4: =M7+O7 -> 45084.3 | O4: =M4-N4 -> 25926.7
A5: 45538 | H5: ='9月費用明細憑證'!E5 -> 0 | I5: =H5+(F5*0.7) -> 0 | J5: =(B5-C5-D5-E5-G5-I5) -> 0 | L5: 銀行帳戶 | M5: 76 | O5: =M5-N5 -> 76 | P5: =M5-N5 -> 76
A6: 45539 | H6: ='9月費用明細憑證'!E6 -> 0 | I6: =H6+(F6*0.7) -> 0 | J6: =(B6-C6-D6-E6-G6-I6) -> 0 | L6: 現金帳餘額 | M6: =M10+M9 -> 25926.7 | O6: =M6-N6 -> 25926.7
A7: 45540 | H7: ='9月費用明細憑證'!E7 -> 0 | I7: =H7+(F7*0.7) -> 0 | J7: =(B7-C7-D7-E7-G7-I7) -> 0 | L7: 各項費用 | M7: =C35 -> 41179 | N7: 代銷成本 | O7: =F35 -> 3905.3
A8: 45541 | H8: ='9月費用明細憑證'!E8 -> 0 | I8: =H8+(F8*0.7) -> 0 | J8: =(B8-C8-D8-E8-G8-I8) -> 0
A9: 45542 | H9: ='9月費用明細憑證'!E9 -> 0 | I9: =H9+(F9*0.7) -> 0 | J9: =(B9-C9-D9-E9-G9-I9) -> 0 | L9: 公司戶進出 | M9: 20000
A10: 45543 | H10: ='9月費用明細憑證'!E10 -> 0 | I10: =H10+(F10*0.7) -> 0 | J10: =(B10-C10-D10-E10-G10-I10) -> 0 | L10: 稅前毛利 | M10: =O3 -> 5926.7
A11: 45544 | H11: ='9月費用明細憑證'!E11 -> 0 | I11: =H11+(F11*0.7) -> 0 | J11: =(B11-C11-D11-E11-G11-I11) -> 0 | L11: 人事費 | M11: 0
A12: 45545 | H12: ='9月費用明細憑證'!E12 -> 0 | I12: =H12+(F12*0.7) -> 0 | J12: =(B12-C12-D12-E12-G12-I12) -> 0 | L12: 當月損益 | M12: =M10-M11 -> 5926.7
A13: 45546 | H13: ='9月費用明細憑證'!E13 -> 0 | I13: =H13+(F13*0.7) -> 0 | J13: =(B13-C13-D13-E13-G13-I13) -> 0
A14: 45547 | H14: ='9月費用明細憑證'!E14 -> 0 | I14: =H14+(F14*0.7) -> 0 | J14: =(B14-C14-D14-E14-G14-I14) -> 0
A15: 45548 | H15: ='9月費用明細憑證'!E15 -> 1585 | I15: =H15+(F15*0.7) -> 1585 | J15: =(B15-C15-D15-E15-G15) -> 0
A16: 45549 | B16: 6906 | C16: 7001 | F16: 250 | H16: ='9月費用明細憑證'!E16 -> 0 | I16: =H16+(F16*0.7) -> 175 | J16: =(B16-C16-D16-E16-G16) -> -95 | L16: 紅字→多錢
A17: 45550 | B17: 1632 | C17: =2947-780 -> 2167 | F17: 140 | H17: ='9月費用明細憑證'!E17 -> 0 | I17: =H17+(F17*0.7) -> 98 | J17: =(B17-C17-D17-E17-G17) -> -535 | L17: 黑字→少錢
A18: 45551 | B18: 2767 | C18: 3100 | F18: 170 | H18: ='9月費用明細憑證'!E18 -> 0 | I18: =H18+(F18*0.7) -> 119 | J18: =(B18-C18-D18-E18-G18) -> -333
A19: 45552 | B19: 3703 | C19: =2300+1265 -> 3565 | F19: 60 | H19: ='9月費用明細憑證'!E19 -> 1265 | I19: =H19+(F19*0.7) -> 1307 | J19: =(B19-C19-D19-E19-G19) -> 138
A20: 45553 | B20: 2296 | C20: 2515 | F20: 30 | H20: ='9月費用明細憑證'!E20 -> 3515 | I20: =H20+(F20*0.7) -> 3536 | J20: =(B20-C20-D20-E20-G20) -> -219
A21: 45554 | B21: 2415 | C21: 2353 | F21: 370 | H21: ='9月費用明細憑證'!E21 -> 4540 | I21: =H21+(F21*0.7) -> 4799 | J21: =(B21-C21-D21-E21-G21) -> 62
A22: 45555 | B22: 2732 | C22: 2300 | F22: 0 | H22: ='9月費用明細憑證'!E22 -> 11284 | I22: =H22+(F22*0.7) -> 11284 | J22: =(B22-C22-D22-E22-G22) -> 432
A23: 45556 | B23: 2598 | C23: 2600 | F23: 405 | H23: ='9月費用明細憑證'!E23 -> 250 | I23: =H23+(F23*0.7) -> 533.5 | J23: =(B23-C23-D23-E23-G23) -> -2
A24: 45557 | B24: 2456 | C24: 3012 | F24: 824 | H24: ='9月費用明細憑證'!E24 -> 880 | I24: =H24+(F24*0.7) -> 1456.8 | J24: =(B24-C24-D24-E24-G24) -> -556
A25: 45558 | B25: 2426 | C25: 3023 | F25: 900 | H25: ='9月費用明細憑證'!E25 -> 6905 | I25: =H25+(F25*0.7) -> 7535 | J25: =(B25-C25-D25-E25-G25) -> -597
A26: 45559 | B26: 2340 | C26: 2800 | F26: 255 | H26: ='9月費用明細憑證'!E26 -> 0 | I26: =H26+(F26*0.7) -> 178.5 | J26: =(B26-C26-D26-E26-G26) -> -460
A27: 45560 | B27: 2252 | C27: 2867 | F27: =270+120 -> 390 | H27: ='9月費用明細憑證'!E27 -> 935 | I27: =H27+(F27*0.7) -> 1208 | J27: =(B27-C27-D27-E27-G27) -> -615
A28: 45561 | B28: 3353 | C28: 2842 | F28: =200+120+40 -> 360 | H28: ='9月費用明細憑證'!E28 -> 880 | I28: =H28+(F28*0.7) -> 1132 | J28: =(B28-C28-D28-E28-G28) -> 511
A29: 45562 | B29: 3056 | C29: 3200 | F29: =180+50 -> 230 | H29: ='9月費用明細憑證'!E29 -> 0 | I29: =H29+(F29*0.7) -> 161 | J29: =(B29-C29-D29-E29-G29) -> -144
A30: 45563 | B30: 3081 | C30: 3300 | F30: =345+50 -> 395 | H30: ='9月費用明細憑證'!E30 -> 5486 | I30: =H30+(F30*0.7) -> 5762.5 | J30: =(B30-C30-D30-E30-G30) -> -219
A31: 45564 | B31: 1550 | C31: 1666 | F31: 520 | H31: ='9月費用明細憑證'!E31 -> 0 | I31: =H31+(F31*0.7) -> 364 | J31: =(B31-C31-D31-E31-G31) -> -116
A32: 45565 | B32: 2445 | C32: 2700 | F32: =240+40 -> 280 | H32: ='9月費用明細憑證'!E32 -> 3654 | I32: =H32+(F32*0.7) -> 3850 | J32: =(B32-C32-D32-E32-G32) -> -255
A34: 項目 | B34: 月營業額 | C34: 費用總額 | D34: 毛利 | F34: 烘爸帳款 | G34: 帳面餘絀 | H34: 每股可分淨額
A35: 小計 | B35: =SUM(B3:B33) -> 48008 | C35: =SUM(H3:H33) -> 41179 | D35: =B35-C35 -> 6829 | F35: =SUM(F3:F33)*0.7 -> 3905.3 | G35: =SUM(J3:J33) -> -3003 | H35: =O8/3 -> 0

Sheet 9月費用明細憑證
A1: 聊閣咖啡仁義店支出費用明細
A2: 費用明細表 | B2: 食材成本 | C2: 固定成本 | D2: 變動成本 | E2: 費用小計 | F2: 項目明細 | G2: 支付憑證
A3: 45536 | E3: =SUM(B3:D3) -> 0 | G3: 9月憑證
A4: 45537 | E4: =SUM(B4:D4) -> 0
A5: 45538 | E5: =SUM(B5:D5) -> 0
A6: 45539 | E6: =SUM(B6:D6) -> 0
A7: 45540 | E7: =SUM(B7:D7) -> 0
A8: 45541 | E8: =SUM(B8:D8) -> 0
A9: 45542 | E9: =SUM(B9:D9) -> 0
A10: 45543 | E10: =SUM(B10:D10) -> 0
A11: 45544 | E11: =SUM(B11:D11) -> 0
A12: 45545 | E12: =SUM(B12:D12) -> 0
A13: 45546 | E13: =SUM(B13:D13) -> 0
A14: 45547 | E14: =SUM(B14:D14) -> 0
A15: 45548 | B15: 1585 | E15: =SUM(B15:D15) -> 1585 | F15: 開元 1570 匯費 15
A16: 45549 | E16: =SUM(B16:D16) -> 0
A17: 45550 | E17: =SUM(B17:D17) -> 0
A18: 45551 | E18: =SUM(B18:D18) -> 0
A19: 45552 | B19: 1265 | E19: =SUM(B19:D19) -> 1265 | F19: 鮮奶 1250 匯費 15
A20: 45553 | B20: 3515 | E20: =SUM(B20:D20) -> 3515 | F20: 茶葉 3500 匯費 15
A21: 45554 | B21: 4540 | E21: =SUM(B21:D21) -> 4540 | F21: 蔓越莓茶包 4540
A22: 45555 | B22: =8640+1020 -> 9660 | D22: =1550+59+15 -> 1624 | E22: =SUM(B22:D22) -> 11284 | F22: 咖啡豆 8640 匯費 15 咖啡器具 1550 開元 1020 洗手乳 59
A23: 45556 | B23: 235 | D23: 15 | E23: =SUM(B23:D23) -> 250 | F23: 厚片 235 匯費 15
A24: 45557 | D24: 880 | E24: =SUM(B24:D24) -> 880 | F24: 福利（生日禮金） 880
A25: 45558 | D25: =6890+15 -> 6905 | E25: =SUM(B25:D25) -> 6905 | F25: 易達豐 6890 匯費15
A26: 45559 | E26: =SUM(B26:D26) -> 0
A27: 45560 | B27: 920 | D27: 15 | E27: =SUM(B27:D27) -> 935 | F27: 開元 920 匯費 15
A28: 45561 | D28: 880 | E28: =SUM(B28:D28) -> 880 | F28: 員工生日 880
A29: 45562 | E29: =SUM(B29:D29) -> 0
A30: 45563 | B30: 1000 | D30: =2714+1757+15 -> 4486 | E30: =SUM(B30:D30) -> 5486 | F30: 裝潢雜支 2714 公司健保 1757 品皇 1000 匯費 15
A31: 45564 | E31: =SUM(B31:D31) -> 0
A32: 45565 | B32: =895 -> 895 | D32: =790+382+402+45+1140 -> 2759 | E32: =SUM(B32:D32) -> 3654 | F32: 開元 895 易達豐 790 玻璃杯 402 咖啡器具 382 匯費 45
A33: 未結應付賬款
A34: 小計 | E34: =SUM(E3:E32) -> 41179
